Workbook

Sheet Разлики
A1: Склад за дост. | B1: Доставчик | C1: Vendor No | D1: Начин на подаване | E1: Номер прием | F1: Вътрешен номер | G1: Активен номер | H1: Delivery No | I1: Invoice No | J1: Invoice Date | K1: Ref. Number SUPPLIER | L1: Other Supplier Ref Num | M1: Price | N1: QTY | O1: Received QTY | P1: Difference | Q1: Подал разликата | R1: Стойност във валутата на доставчика | S1: Стойност (в лева) | T1: Дата на подаване | U1: СТАТУС - Попълва се от централата! | V1: № документа за разлики | W1: Дата на документа за разлики | X1: При фактура - дата на приема в Навижън | Y1: Обработени в B01 | Z1: Номер на клетка за минуси | AA1: Намерени БРОЙКИ (след подаването им) | AB1: Подадена информация към дост. за намерени бройки след подаването им (ДАТА) | AC1: Допълнителен коментар | AD1: ДАТА на намиране в В01 на липсващи артикули или коментар от склада | AE1: дата на прием в Навижън | AF1: working days after goods receipt in navision | AG1: БРАНД | AH1: РМ | AI1: формула Ники | AJ1: INV | AK1: INV | AL1: INV positiv | AM1: Разлика между + и инв. | AN1: дата на прием от таблицата на Тони | AO1: номер на склада - програмата | AP1: системен номер на доставка на склада
A2: B01 | B2: AISIN EUROPE SA | C2: VEN0000901 | D2: =IFERROR(HYPERLINK(INDEX(вендори!F:F,MATCH(C2,вендори!A:A,0)),INDEX(вендори!F:F,MATCH(C2,вендори!A:A,0))),"") -> 0 | E2: 25136237 | F2: BF3841 | G2: AISWPT-181 | H2: 313086 | I2: 25136237 | J2: 45952 | K2: WPT-181 | M2: 34,02 | N2: 0 | O2: 8 | P2: 8 | Q2: Плюс | R2: 272.16 | S2: 532.29869 | T2: 45972 | U2: Отказани | AE2: 45965 | AF2: 6 | AI2: 25136237|BF3841 | AN2: 45758 | AO2: 16128 | AP2: 7195
A3: B01 | B3: Auger Autotechnik GmbH | C3: VEN0001821 | D3: =IFERROR(HYPERLINK(INDEX(вендори!F:F,MATCH(C3,вендори!A:A,0)),INDEX(вендори!F:F,MATCH(C3,вендори!A:A,0))),"") -> 0 | E3: 95091282 | F3: C65242 | G3: AUG70793 | H3: 80220627 | I3: 95091282 | J3: 45946 | K3: 70793 | L3: 70793 | M3: 7.77 | N3: 12 | O3: 6 | P3: -6 | Q3: Минус | R3: -46.62 | S3: -91.180795 | T3: 45972 | U3: Получено КИ | V3: 10028768 | W3: 45975 | AE3: 45960 | AF3: 9 | AG3: AUGER | AH3: MKEHAYOVA | AI3: 95091282|C65242 | AN3: 45788 | AO3: 16178 | AP3: 7093
A4: B01 | B4: CARPASSION SP. ZO.O | C4: VEN0002939 | D4: =IFERROR(HYPERLINK(INDEX(вендори!F:F,MATCH(C4,вендори!A:A,0)),INDEX(вендори!F:F,MATCH(C4,вендори!A:A,0))),"") -> 0 | E4: FS113102025CARP | F4: H1393F | G4: CP 10061CP | H4: FS/113/10/2025/CARP | I4: FS/113/10/2025/CARP | J4: 45950 | K4: CP 10061CP | L4: 0 | M4: 8.84 | N4: 4 | O4: 0 | P4: -4 | Q4: Минус | R4: -35.36 | S4: -69.158149 | T4: 45972 | U4: МАСЛА - обработва се от РМ | AE4: 45966 | AF4: 5 | AG4: CARPASSION | AH4: ALAZAROV | AI4: FS113102025CARP|H1393F | AN4: 45911 | AO4: 16392 | AP4: 7296
A5: B01 | B5: CARPASSION SP. ZO.O | C5: VEN0002939 | D5: =IFERROR(HYPERLINK(INDEX(вендори!F:F,MATCH(C5,вендори!A:A,0)),INDEX(вендори!F:F,MATCH(C5,вендори!A:A,0))),"") -> 0 | E5: FS113102025CARP | F5: C4BD8B | G5: MMT CP10061 | H5: FS/113/10/2025/CARP | I5: FS/113/10/2025/CARP | J5: 45950 | K5: 10061 | L5: 10061__10061 | M5: 8.84 | N5: 50 | O5: 54 | P5: 4 | Q5: Плюс | R5: 35.36 | S5: 69.158149 | T5: 45972 | U5: МАСЛА - обработва се от РМ | AE5: 45966 | AF5: 5 | AG5: CARPASSION | AH5: ALAZAROV | AI5: FS113102025CARP|C4BD8B | AN5: 45911 | AO5: 16393 | AP5: 7296
A6: B01 | B6: CMI Filtration Belgium | C6: VEN0002552 | D6: =IFERROR(HYPERLINK(INDEX(вендори!F:F,MATCH(C6,вендори!A:A,0)),INDEX(вендори!F:F,MATCH(C6,вендори!A:A,0))),"") -> 0 | E6: 1040023819 | F6: F4A6B4 | G6: FF253 | H6: 19374240 | I6: 1040023819 | J6: 45950 | K6: FF0025300MF | L6: FF0025300MF | M6: 8.9 | N6: 12 | O6: 2 | P6: -10 | Q6: Минус | R6: -89 | S6: -174.06887 | T6: 45972 | U6: Получено КИ | V6: 5000005053 | W6: 45996 | AE6: 45958 | AF6: 11 | AG6: FLEETGUARD | AH6: VAPETROV | AI6: 1040023819|F4A6B4 | AN6: 30/10/2025 | AO6: 15908 | AP6: 7041
A7: B01 | B7: ContiTech Antriebssysteme GmbH | C7: VEN0000263 | D7: =IFERROR(HYPERLINK(INDEX(вендори!F:F,MATCH(C7,вендори!A:A,0)),INDEX(вендори!F:F,MATCH(C7,вендори!A:A,0))),"") -> деливъри | E7: 9956682 | F7: F8C210 | G7: CT 1218 | H7: 33056367 | I7: 9956682 | J7: 45930 | K7: CT1218 | L7: CT1218 | M7: 7.06 | N7: 246 | O7: 146 | P7: -100 | Q7: Минус | R7: -706 | S7: -1380.816 | T7: 45972 | U7: Получено КИ | V7: 3000130827 | W7: 46051 | X7: по сметка | AC7: вече са инв. | AE7: 45938 | AF7: 25 | AG7: CONTITECH | AH7: VAPETROV | AI7: 9956682|F8C210 | AN7: 45910 | AO7: 14348 | AP7: 6402
A8: B01 | B8: ContiTech Antriebssysteme GmbH | C8: VEN0000263 | D8: =IFERROR(HYPERLINK(INDEX(вендори!F:F,MATCH(C8,вендори!A:A,0)),INDEX(вендори!F:F,MATCH(C8,вендори!A:A,0))),"") -> деливъри | E8: 9956682 | F8: G109Z0 | G8: 6 PK 1033 K1 | H8: 33056367 | I8: 9956682 | J8: 45930 | K8: 6PK1033K1 | L8: 6PK1033K1 | M8: 24.16 | N8: 23 | O8: 21 | P8: -2 | Q8: Минус | R8: -48.32 | S8: -94.505706 | T8: 45972 | U8: Получено КИ | V8: 3000130827 | W8: 46051 | X8: по сметка | AC8: вече са инв. | AE8: 45938 | AF8: 25 | AG8: CONTITECH | AH8: VAPETROV | AI8: 9956682|G109Z0 | AN8: 45910 | AO8: 14347 | AP8: 6402
A9: B01 | B9: ContiTech Antriebssysteme GmbH | C9: VEN0000263 | D9: =IFERROR(HYPERLINK(INDEX(вендори!F:F,MATCH(C9,вендори!A:A,0)),INDEX(вендори!F:F,MATCH(C9,вендори!A:A,0))),"") -> деливъри | E9: 9961090 | F9: E79DA3 | G9: CT 1099 WP1 | H9: 33079802 | I9: 9961090 | J9: 45951 | K9: CT1099WP1 | L9: CT1099WP1 | M9: 92.04 | N9: 9 | O9: 8 | P9: -1 | Q9: Минус | R9: -92.04 | S9: -180.01459 | T9: 45972 | U9: Подадена | AE9: 45960 | AF9: 9 | AG9: CONTITECH | AH9: VAPETROV | AI9: 9961090|E79DA3 | AN9: 31/10/2025 | AO9: 15964 | AP9: 7134
A10: B01 | B10: ContiTech Antriebssysteme GmbH | C10: VEN0000263 | D10: =IFERROR(HYPERLINK(INDEX(вендори!F:F,MATCH(C10,вендори!A:A,0)),INDEX(вендори!F:F,MATCH(C10,вендори!A:A,0))),"") -> деливъри | E10: 9961090 | F10: A6754D | G10: CT 1092 K1 | H10: 33079802 | I10: 9961090 | J10: 45951 | K10: CT1092K1 | M10: 37.67 | N10: 0 | O10: 1 | P10: 1 | Q10: Плюс | R10: 37.67 | S10: 73.676116 | T10: 45972 | U10: Получено ДИ/фактура | V10: 3000130828 | W10: 46051 | AE10: 45961 | AF10: 8 | AI10: 9961090|A6754D | AN10: 31/10/2025 | AO10: 15967 | AP10: 7134
A11: B01 | B11: ContiTech Antriebssysteme GmbH | C11: VEN0000263 | D11: =IFERROR(HYPERLINK(INDEX(вендори!F:F,MATCH(C11,вендори!A:A,0)),INDEX(вендори!F:F,MATCH(C11,вендори!A:A,0))),"") -> деливъри | E11: 9961090 | F11: A79B9D | G11: 7 PK 2035 | H11: 33079802 | I11: 9961090 | J11: 45951 | K11: 7PK2035 | L11: 7PK2035 | M11: 13.18 | N11: 160 | O11: 170 | P11: 10 | Q11: Плюс | R11: 131.8 | S11: 257.77839 | T11: 45972 | U11: Получено ДИ/фактура | V11: 3000130828 | W11: 46051 | AE11: 45960 | AF11: 9 | AG11: CONTITECH | AH11: VAPETROV | AI11: 9961090|A79B9D | AN11: 31/10/2025 | AO11: 15969 | AP11: 7134
A12: B01 | B12: DENSO Europe B.V. | C12: VEN0001937 | D12: =IFERROR(HYPERLINK(INDEX(вендори!F:F,MATCH(C12,вендори!A:A,0)),INDEX(вендори!F:F,MATCH(C12,вендори!A:A,0))),"") -> 0 | E12: TA25024769 | F12: D2EC6C | G12: DCRI300460 | H12: 1157003 | 1158201 | I12: TA 25024769 | J12: 45947 | K12: DCRI300460 | L12: DCRI300460 | M12: 177.16 | N12: 4 | O12: 3 | P12: -1 | Q12: Минус | R12: -177.16 | S12: -346.49484 | T12: 45972 | U12: Отказани | AE12: 45951 | AF12: 16 | AG12: DENSO | AH12: KMINKOV | AI12: TA25024769|D2EC6C | AN12: 30/10/2025 | AO12: 15891 | AP12: 6809
A13: B01 | B13: DENSO Europe B.V. | C13: VEN0001937 | D13: =IFERROR(HYPERLINK(INDEX(вендори!F:F,MATCH(C13,вендори!A:A,0)),INDEX(вендори!F:F,MATCH(C13,вендори!A:A,0))),"") -> 0 | E13: TA25024769 | F13: 9EDCDA | G13: KJ16CR-L11 | H13: 1157003 | 1158201 | I13: TA 25024769 | J13: 45947 | K13: KJ16CR-L11 | L13: KJ16CR-L11 | M13: 1.39 | N13: 350 | O13: 370 | P13: 20 | Q13: Плюс | R13: 27.8 | S13: 54.372074 | T13: 45972 | U13: Отказани | AE13: 45951 | AF13: 16 | AG13: DENSO | AH13: KMINKOV | AI13: TA25024769|9EDCDA | AN13: 30/10/2025 | AO13: 15892 | AP13: 6809
A14: B01 | B14: DENSO Europe B.V. | C14: VEN0001937 | D14: =IFERROR(HYPERLINK(INDEX(вендори!F:F,MATCH(C14,вендори!A:A,0)),INDEX(вендори!F:F,MATCH(C14,вендори!A:A,0))),"") -> 0 | E14: TA25025315 | F14: B2A864 | G14: DCP17023 | H14: TA | 25025315 | I14: TA 25025315 | J14: 45952 | K14: DCP17023 | L14: DCP17023 | M14: 193 | N14: 2 | O14: 0 | P14: -2 | Q14: Минус | R14: -386 | S14: -754.95038 | T14: 45972 | U14: Отказани | AE14: 45959 | AF14: 10 | AG14: DENSO | AH14: KMINKOV | AI14: TA25025315|B2A864 | AN14: 45668 | AO14: 16041 | AP14: 7074
A15: B01 | B15: DENSO Europe B.V. | C15: VEN0001937 | D15: =IFERROR(HYPERLINK(INDEX(вендори!F:F,MATCH(C15,вендори!A:A,0)),INDEX(вендори!F:F,MATCH(C15,вендори!A:A,0))),"") -> 0 | E15: TA25025315 | F15: CFE3A3 | G15: DRR09034 | H15: TA | 25025315 | I15: TA 25025315 | J15: 45952 | K15: DRR09034 | L15: DRR09034 | M15: 31.3 | N15: 22 | O15: 21 | P15: -1 | Q15: Минус | R15: -31.3 | S15: -61.217479 | T15: 45972 | U15: Отказани | AE15: 45959 | AF15: 10 | AG15: DENSO | AH15: KMINKOV | AI15: TA25025315|CFE3A3 | AN15: 45668 | AO15: 16042 | AP15: 7074
A16: B01 | B16: DIESEL TECHNIC SE | C16: VEN0001277 | D16: =IFERROR(HYPERLINK(INDEX(вендори!F:F,MATCH(C16,вендори!A:A,0)),INDEX(вендори!F:F,MATCH(C16,вендори!A:A,0))),"") -> https://partnerportal.dieseltechnic.com/en/infocenter/forms | E16: BCI0758795 | F16: D4A2AA | G16: 7.49010 | H16: BCI0758795 | I16: BCI0758795 | J16: 45950 | K16: 7.49010 | L16: 7.49010 | M16: 161.11 | N16: 1 | O16: 0 | P16: -1 | Q16: Минус | R16: -161.11 | S16: -315.10377 | T16: 45972 | U16: Получено КИ | V16: BCC0179970 + ДИ BCI0770360/27.11.25 | W16: 45978 | X16: по сметка | AA16: 1 | AB16: 45987 | AC16: поскано ДИ - ок | AD16: 45986 | AE16: 45957 | AF16: 12 | AG16: DT | AH16: AGEORGIEV | AI16: BCI0758795|D4A2AA | AN16: 45819 | AO16: 16205 | AP16: 6994
A17: B01 | B17: DIESEL TECHNIC SE | C17: VEN0001277 | D17: =IFERROR(HYPERLINK(INDEX(вендори!F:F,MATCH(C17,вендори!A:A,0)),INDEX(вендори!F:F,MATCH(C17,вендори!A:A,0))),"") -> https://partnerportal.dieseltechnic.com/en/infocenter/forms | E17: BCI0760404 | F17: F5271B | G17: 4.90772 | H17: BCS2114647 | I17: BCI0760404 | J17: 45954 | K17: 4.90772 | L17: 4.90772 | M17: 0.76 | N17: 1000 | O17: 1101 | P17: 101 | Q17: Плюс | R17: 76.76 | S17: 150.12951 | T17: 45972 | U17: Получено ДИ/фактура | V17: BCI0766921 | W17: 45978 | X17: CM 19.11.25 | AE17: 45960 | AF17: 9 | AG17: DT | AH17: KDOBREV | AI17: BCI0760404|F5271B | AN17: 45727 | AO17: 16058 | AP17: 7142
A18: B01 | B18: EXEDY CLUTCH EUROPE LIMITED | C18: VEN0002388 | D18: =IFERROR(HYPERLINK(INDEX(вендори!F:F,MATCH(C18,вендори!A:A,0)),INDEX(вендори!F:F,MATCH(C18,вендори!A:A,0))),"") -> 0 | E18: PSI065267 | F18: BBA0C4 | G18: NSS2198 | H18: PSI065267 | I18: PSI065267 | J18: 45958 | K18: NSS2198 | L18: NSS2198 | M18: 77.96 | N18: 3 | O18: 0 | P18: -3 | Q18: Минус | R18: -233.88 | S18: -457.42952 | T18: 45972 | U18: Анулирана | AE18: 45966 | AF18: 5 | AG18: EXEDY | AH18: AGEORGIEV | AI18: PSI065267|BBA0C4 | AN18: 45819 | AO18: 16221 | AP18: 7319
A19: B01 | B19: EXEDY CLUTCH EUROPE LIMITED | C19: VEN0002388 | D19: =IFERROR(HYPERLINK(INDEX(вендори!F:F,MATCH(C19,вендори!A:A,0)),INDEX(вендори!F:F,MATCH(C19,вендори!A:A,0))),"") -> 0 | E19: PSI065267 | F19: XXXX | G19: NS656152 | H19: PSI065267 | I19: PSI065267 | J19: 45958 | K19: NS656152 | M19: 77.96 | N19: 0 | O19: 3 | P19: 3 | Q19: Плюс | R19: 233.88 | S19: 457.42952 | T19: 45972 | U19: Анулирана | AC19: АГ - не излиза, да искаме връщане/Exedy Japan’s part number for ECE NSS2198 = NS656152 | AE19: 45966 | AF19: 5 | AI19: PSI065267|XXXX | AN19: 45819 | AO19: 16222 | AP19: 7319
A20: B01 | B20: FEDERAL-MOGUL GLOBAL AFTERMARKET EMEA BV | C20: VEN0001842 | D20: =IFERROR(HYPERLINK(INDEX(вендори!F:F,MATCH(C20,вендори!A:A,0)),INDEX(вендори!F:F,MATCH(C20,вендори!A:A,0))),"") -> https://afjt3vcvh.accounts.ondemand.com/saml2/idp/sso/afjt3vcvh.accounts.ondemand.com | E20: 3000682023 | F20: G0KLUF | G20: FOL252 | H20: 34587751 | 34587752 | 34587753 | 34587754 | 34587755 | 34587756 | I20: 3000682023 | J20: 45952 | K20: FOL252 | L20: FOL252__FOL252 | M20: 9.14 | N20: 16 | O20: 0 | P20: -16 | Q20: Минус | R20: -146.24 | S20: -286.02058 | T20: 45972 | U20: Отказани | AA20: 16 | AB20: ок | AC20: Ticket Number: 336733 | AD20: 45994 | AE20: 45957 | AF20: 12 | AG20: AE | AH20: AGEORGIEV | AI20: 3000682023|G0KLUF | AN20: 45668 | AO20: 16011 | AP20: 6988
A21: B01 | B21: FERDINAND BILSTEIN GMBH + CO. KG | C21: VEN0001136 | D21: =IFERROR(HYPERLINK(INDEX(вендори!F:F,MATCH(C21,вендори!A:A,0)),INDEX(вендори!F:F,MATCH(C21,вендори!A:A,0))),"") -> 0 | E21: 12417309 | F21: D16439 | G21: FE40372 | H21: 708644501 | 708644756 | I21: 12417309 | J21: 45943 | K21: 40372 | L21: 40372 | M21: 28.35 | N21: 2 | O21: 0 | P21: -2 | Q21: Минус | R21: -56.7 | S21: -110.89556 | T21: 45972 | U21: Получено КИ | V21: 93276984 | W21: 45975 | AE21: 45950 | AF21: 17 | AG21: FEBI | AH21: KDOBREV | AI21: 12417309|D16439 | AN21: 29/10/2025 | AO21: 15827 | AP21: 6790
A22: B01 | B22: FERDINAND BILSTEIN GMBH + CO. KG | C22: VEN0001136 | D22: =IFERROR(HYPERLINK(INDEX(вендори!F:F,MATCH(C22,вендори!A:A,0)),INDEX(вендори!F:F,MATCH(C22,вендори!A:A,0))),"") -> 0 | E22: 12422146 | F22: C354B1 | G22: FE34367 | H22: 708685998 | 708686069 | I22: 12422146 | J22: 45951 | K22: 34367 | L22: 34367 | M22: 4.32 | N22: 56 | O22: 0 | P22: -56 | Q22: Минус | R22: -241.92 | S22: -473.15439 | T22: 45972 | U22: Отказани | AE22: 45959 | AF22: 10 | AG22: FEBI | AH22: KDOBREV | AI22: 12422146|C354B1 | AN22: 45880 | AO22: 16336 | AP22: 7060
A23: B01 | B23: FERDINAND BILSTEIN GMBH + CO. KG | C23: VEN0001136 | D23: =IFERROR(HYPERLINK(INDEX(вендори!F:F,MATCH(C23,вендори!A:A,0)),INDEX(вендори!F:F,MATCH(C23,вендори!A:A,0))),"") -> 0 | E23: 12422146 | F23: G13CNO | G23: FE179812 | H23: 708685998 | 708686069 | I23: 12422146 | J23: 45951 | K23: 179812 | L23: 179812 | M23: 130.59 | N23: 1 | O23: 0 | P23: -1 | Q23: Минус | R23: -130.59 | S23: -255.41184 | T23: 45972 | U23: Отказани | AE23: 45959 | AF23: 10 | AG23: FEBI | AH23: MKEHAYOVA | AI23: 12422146|G13CNO | AN23: 45880 | AO23: 16333 | AP23: 7060
A24: B01 | B24: FERDINAND BILSTEIN GMBH + CO. KG | C24: VEN0001136 | D24: =IFERROR(HYPERLINK(INDEX(вендори!F:F,MATCH(C24,вендори!A:A,0)),INDEX(вендори!F:F,MATCH(C24,вендори!A:A,0))),"") -> 0 | E24: 12422146 | F24: B9F387 | G24: FE32232 | H24: 708685998 | 708686069 | I24: 12422146 | J24: 45951 | K24: 32232 | L24: 32232 | M24: 63.2 | N24: 2 | O24: 1 | P24: -1 | Q24: Минус | R24: -63.2 | S24: -123.60846 | T24: 45972 | U24: Отказани | AE24: 45959 | AF24: 10 | AG24: FEBI | AH24: KDOBREV | AI24: 12422146|B9F387 | AN24: 45880 | AO24: 16335 | AP24: 7060
A25: B01 | B25: FERDINAND BILSTEIN GMBH + CO. KG | C25: VEN0001136 | D25: =IFERROR(HYPERLINK(INDEX(вендори!F:F,MATCH(C25,вендори!A:A,0)),INDEX(вендори!F:F,MATCH(C25,вендори!A:A,0))),"") -> 0 | E25: 12422146 | F25: CFB629 | G25: FE38839 | H25: 708685998 | 708686069 | I25: 12422146 | J25: 45951 | K25: 38839 | M25: 35.99 | N25: 0 | O25: 1 | P25: 1 | Q25: Плюс | R25: 35.99 | S25: 70.390322 | T25: 45972 | U25: Отказани | AE25: 45959 | AF25: 10 | AI25: 12422146|CFB629 | AN25: 45880 | AO25: 16339 | AP25: 7060
A26: B01 | B26: FRECCIA INTERNATIONAL S.R.L. | C26: VEN0001243 | D26: =IFERROR(HYPERLINK(INDEX(вендори!F:F,MATCH(C26,вендори!A:A,0)),INDEX(вендори!F:F,MATCH(C26,вендори!A:A,0))),"") -> бланка | E26: 408825 | F26: G0POK1 | G26: RA06-998 | H26: 4088/25 | I26: 4088/25 | J26: 45946 | K26: RA06-998 | L26: RA06-998 | M26: 3.66 | N26: 128 | O26: 176 | P26: 48 | Q26: Плюс | R26: 175.68 | S26: 343.60021 | T26: 45972 | U26: Получено ДИ/фактура | V26: 5140/25 | W26: 46010 | X26: CM 16.01.26 | AE26: 45966 | AF26: 5 | AG26: FRECCIA | AH26: AGEORGIEV | AI26: 408825|G0POK1 | AN26: 45849 | AO26: 16328 | AP26: 7292
A27: B01 | B27: FROGUM SP. Z O.O. | C27: VEN0002039 | D27: =IFERROR(HYPERLINK(INDEX(вендори!F:F,MATCH(C27,вендори!A:A,0)),INDEX(вендори!F:F,MATCH(C27,вендори!A:A,0))),"") -> 0 | E27: 65/10/SU/2025 | F27: C6364F | G27: MMT A040 0077 | H27: номер на доставка 6787 | I27: 65/10/SU/2025 | J27: 45946 | K27: MMT A040 0077 | L27: 0 | M27: 13.03 | N27: 11 | O27: 4 | P27: -7 | Q27: Минус | R27: -91.21 | S27: -178.39125 | T27: 45972 | U27: Получено КИ | V27: 6/11/SU/2025 | W27: 45979 | AE27: 45950 | AF27: 17 | AG27: FROGUM | AH27: ALAZAROV | AI27: 65/10/SU/2025|C6364F | AN27: 31/10/2025 | AO27: 15954 | AP27: -
A28: B01 | B28: FROGUM SP. Z O.O. | C28: VEN0002039 | D28: =IFERROR(HYPERLINK(INDEX(вендори!F:F,MATCH(C28,вендори!A:A,0)),INDEX(вендори!F:F,MATCH(C28,вендори!A:A,0))),"") -> 0 | E28: 65/10/SU/2025 | F28: C63662 | G28: MMT A040 00781 | H28: номер на доставка 6787 | I28: 65/10/SU/2025 | J28: 45946 | K28: MMT A040 00781 | L28: 0 | M28: 13.03 | N28: 5 | O28: 0 | P28: -5 | Q28: Минус | R28: -65.15 | S28: -127.42232 | T28: 45972 | U28: Получено КИ | V28: 6/11/SU/2025 | W28: 45979 | AE28: 45950 | AF28: 17 | AG28: FROGUM | AH28: ALAZAROV | AI28: 65/10/SU/2025|C63662 | AN28: 31/10/2025 | AO28: 15955 | AP28: -
A29: B01 | B29: FROGUM SP. Z O.O. | C29: VEN0002039 | D29: =IFERROR(HYPERLINK(INDEX(вендори!F:F,MATCH(C29,вендори!A:A,0)),INDEX(вендори!F:F,MATCH(C29,вендори!A:A,0))),"") -> 0 | E29: 65/10/SU/2025 | F29: C63646 | G29: MMT A040 0070 | H29: номер на доставка 6787 | I29: 65/10/SU/2025 | J29: 45946 | K29: MMT A040 0070 | M29: 13,03 | N29: 0 | O29: 6 | P29: 6 | Q29: Плюс | R29: 78.18 | S29: 152.90679 | T29: 45972 | U29: Получено ДИ/фактура | V29: 78/11/SU/2025 | W29: 45979 | X29: 45981 | AE29: 45950 | AF29: 17 | AI29: 65/10/SU/2025|C63646 | AN29: 31/10/2025 | AO29: 15956 | AP29: -
A30: B01 | B30: FUCHS LUBRICANTS ROMANIA SRL | C30: VEN0002862 | D30: =IFERROR(HYPERLINK(INDEX(вендори!F:F,MATCH(C30,вендори!A:A,0)),INDEX(вендори!F:F,MATCH(C30,вендори!A:A,0))),"") -> 0 | E30: FAFLRO2411279 | F30: G10U25 | G30: TITAN FFL-8 1L | H30: ALFRO24/11309 | I30: FAFLRO24/11279 | J30: 45959 | K30: 0 | L30: 0 | M30: 8.5 | N30: 12 | O30: 0 | P30: -12 | Q30: Минус | R30: -102 | S30: -199.49466 | T30: 45972 | U30: МАСЛА - обработва се от РМ | AE30: 45960 | AF30: 9 | AG30: FUCHS | AH30: MDRINEV | AI30: FAFLRO2411279|G10U25 | AN30: 45668 | AO30: 16033 | AP30: 7149
A31: B01 | B31: FUCHS LUBRICANTS ROMANIA SRL | C31: VEN0002862 | D31: =IFERROR(HYPERLINK(INDEX(вендори!F:F,MATCH(C31,вендори!A:A,0)),INDEX(вендори!F:F,MATCH(C31,вендори!A:A,0))),"") -> 0 | E31: FAFLRO2411279 | F31: G0FP87 | G31: TITAN FFL-8 20L | H31: ALFRO24/11309 | I31: FAFLRO24/11279 | J31: 45959 | K31: 602060846 | L31: 0602060846__602060846 | M31: 150.2 | N31: 6 | O31: 4 | P31: -2 | Q31: Минус | R31: -300.4 | S31: -587.53133 | T31: 45972 | U31: МАСЛА - обработва се от РМ | AE31: 45960 | AF31: 9 | AG31: FUCHS | AH31: MDRINEV | AI31: FAFLRO2411279|G0FP87 | AN31: 45668 | AO31: 16034 | AP31: 7149
A32: B01 | B32: GKN Ayra Servicio, S.A | C32: VEN0002007 | D32: =IFERROR(HYPERLINK(INDEX(вендори!F:F,MATCH(C32,вендори!A:A,0)),INDEX(вендори!F:F,MATCH(C32,вендори!A:A,0))),"") -> 0 | E32: 1950287339 | F32: E64EB2 | G32: 0.025552 | H32: 1940479267 | 1940479226 | I32: 1950287339 | J32: 45940 | K32: 25552 | L32: 25552 | M32: 5.73 | N32: 3 | O32: 2 | P32: -1 | Q32: Минус | R32: -5.73 | S32: -11.206906 | T32: 45972 | U32: Получено КИ | V32: 1960063351 | W32: 45974 | AE32: 45951 | AF32: 16 | AG32: SPIDAN | AH32: MKEHAYOVA | AI32: 1950287339|E64EB2 | AN32: 23/10/2025 | AO32: 15371 | AP32: 6824
A33: B01 | B33: GROOTHANDEL TRUCK ONDERDELEN B.V. | C33: VEN0002784 | D33: =IFERROR(HYPERLINK(INDEX(вендори!F:F,MATCH(C33,вендори!A:A,0)),INDEX(вендори!F:F,MATCH(C33,вендори!A:A,0))),"") -> 0 | E33: 25813705 | F33: F80404 | G33: DAF1905555 | H33: 25813705 | I33: 25813705 | J33: 45930 | K33: DAF1905555 | L33: 0 | M33: 39.9 | N33: 2 | O33: 0 | P33: -2 | Q33: Минус | R33: -79.8 | S33: -156.07523 | T33: 45972 | U33: изпратени от дост.впосл. | AC33: You will receive it with the next shipment | AE33: 45960 | AF33: 9 | AG33: DAF | AH33: KMINKOV | AI33: 25813705|F80404 | AN33: 45788 | AO33: 16183 | AP33: 7109
A34: B01 | B34: HELLA POLSKA SP. Z O.O. | C34: VEN0001281 | D34: =IFERROR(HYPERLINK(INDEX(вендори!F:F,MATCH(C34,вендори!A:A,0)),INDEX(вендори!F:F,MATCH(C34,вендори!A:A,0))),"") -> 0 | E34: 4625013258 | F34: 451336 | G34: 1AB007 145-001 | H34: 72676359 | I34: 4625013258 | J34: 45957 | K34: 1AB 007 145-001 | L34: 1AB 007 145-001 | M34: 35.26 | N34: 1 | O34: 0 | P34: -1 | Q34: Минус | R34: -35.26 | S34: -68.962566 | T34: 45972 | U34: Получено КИ | V34: 4725004004 | W34: 45987 | AE34: 45966 | AF34: 5 | AG34: HELLA | AH34: DEIVANOV | AI34: 4625013258|451336 | AN34: 45849 | AO34: 16308 | AP34: 7324
A35: B01 | B35: HENGST SE | C35: VEN0001450 | D35: =IFERROR(HYPERLINK(INDEX(вендори!F:F,MATCH(C35,вендори!A:A,0)),INDEX(вендори!F:F,MATCH(C35,вендори!A:A,0))),"") -> 0 | E35: 90688383 | F35: D92BA0 | G35: E491L | H35: 81919855 | 81919856 | I35: 90688383 | J35: 45953 | K35: E491L | L35: E491L | M35: 29.16 | N35: 12 | O35: 11 | P35: -1 | Q35: Минус | R35: -29.16 | S35: -57.032003 | T35: 45972 | U35: Отказани | AE35: 45961 | AF35: 8 | AG35: HENGST | AH35: VAPETROV | AI35: 90688383|D92BA0 | AN35: 45758 | AO35: 16109 | AP35: 7161
A36: B01 | B36: HENGST SE | C36: VEN0001450 | D36: =IFERROR(HYPERLINK(INDEX(вендори!F:F,MATCH(C36,вендори!A:A,0)),INDEX(вендори!F:F,MATCH(C36,вендори!A:A,0))),"") -> 0 | E36: 90688383 | F36: D93015 | G36: E172H D35 | H36: 81919855 | 81919856 | I36: 90688383 | J36: 45953 | K36: E172H D35 | L36: E172H D35 | M36: 4.14 | N36: 80 | O36: 90 | P36: 10 | Q36: Плюс | R36: 41.4 | S36: 80.971362 | T36: 45972 | U36: Получено ДИ/фактура | V36: 90693897 | W36: 45986 | X36: 45988 | AE36: 45961 | AF36: 8 | AG36: HENGST | AH36: VAPETROV | AI36: 90688383|D93015 | AN36: 45758 | AO36: 16110 | AP36: 7161
A37: B01 | B37: INTER CARS MALTA LIMITED | C37: VEN0001490 | D37: =IFERROR(HYPERLINK(INDEX(вендори!F:F,MATCH(C37,вендори!A:A,0)),INDEX(вендори!F:F,MATCH(C37,вендори!A:A,0))),"") -> 0 | E37: SI25/B01/09/00010 | F37: B4EC94 | G37: C3V022ABE | H37: TCLU2299624 | I37: SI25/B01/09/00010 | J37: 45925 | K37: C3V022ABE | L37: 0 | M37: 11.66 | N37: 64 | O37: 0 | P37: -64 | Q37: Минус | R37: -746.24 | S37: -1305.92 | T37: 45972 | U37: Подадена | AE37: 45938 | AF37: 25 | AG37: ABE | AH37: KDOBREV | AI37: SI25/B01/09/00010|B4EC94 | AN37: 25/10/2025 | AO37: 15564 | AP37: 6373
A38: B01 | B38: INTER CARS MALTA LIMITED | C38: VEN0001490 | D38: =IFERROR(HYPERLINK(INDEX(вендори!F:F,MATCH(C38,вендори!A:A,0)),INDEX(вендори!F:F,MATCH(C38,вендори!A:A,0))),"") -> 0 | E38: SI25/B01/10/00006 | F38: B4CCF5 | G38: C10323ABE | H38: ONEU5768174 | I38: SI25/B01/10/00003 | J38: 45936 | K38: C10323ABE | M38: 4,46 | N38: 110 | O38: 100 | P38: -10 | Q38: Минус | R38: -44.6 | S38: -78.05 | T38: 45972 | U38: Отказани | AE38: 45938 | AF38: 25 | AI38: SI25/B01/10/00006|B4CCF5 | AN38: 45849 | AO38: 16304 | AP38: 6695
A39: B01 | B39: INTER CARS MALTA LIMITED | C39: VEN0001490 | D39: =IFERROR(HYPERLINK(INDEX(вендори!F:F,MATCH(C39,вендори!A:A,0)),INDEX(вендори!F:F,MATCH(C39,вендори!A:A,0))),"") -> 0 | E39: SI25/B01/10/00008 | F39: BEAE41 | G39: AGX088MT | H39: MRKU2726589 | I39: SI25/B01/10/00008 | J39: 45940 | K39: AGX088MT | L39: 0 | M39: 13.96 | N39: 400 | O39: 392 | P39: -8 | Q39: Минус | R39: -111.68 | S39: -195.44 | T39: 45972 | U39: Анулирана | AA39: 8 | AB39: 46002 | AD39: 45993 | AE39: 45958 | AF39: 11 | AG39: MAGNUM TECHNOLOGY | AH39: MKEHAYOVA | AI39: SI25/B01/10/00008|BEAE41 | AN39: 30/10/2025 | AO39: 15904 | AP39: 7014
A40: B01 | B40: INTER CARS MALTA LIMITED | C40: VEN0001490 | D40: =IFERROR(HYPERLINK(INDEX(вендори!F:F,MATCH(C40,вендори!A:A,0)),INDEX(вендори!F:F,MATCH(C40,вендори!A:A,0))),"") -> 0 | E40: SI25/B01/10/00008 | F40: D6223A | G40: AGM088MT | H40: MRKU2726589 | I40: SI25/B01/10/00008 | J40: 45940 | K40: AGM088MT | L40: 0 | M40: 14.54 | N40: 200 | O40: 196 | P40: -4 | Q40: Минус | R40: -58.16 | S40: -101.78 | T40: 45972 | U40: Подадена | AE40: 45958 | AF40: 11 | AG40: MAGNUM TECHNOLOGY | AH40: MKEHAYOVA | AI40: SI25/B01/10/00008|D6223A | AN40: 30/10/2025 | AO40: 15905 | AP40: 7014
A41: B01 | B41: INTER CARS MALTA LIMITED | C41: VEN0001490 | D41: =IFERROR(HYPERLINK(INDEX(вендори!F:F,MATCH(C41,вендори!A:A,0)),INDEX(вендори!F:F,MATCH(C41,вендори!A:A,0))),"") -> 0 | E41: SI25/B01/10/00008 | F41: BEAE42 | G41: AGX089MT | H41: MRKU2726589 | I41: SI25/B01/10/00008 | J41: 45940 | K41: AGX089MT | L41: 0 | M41: 13.96 | N41: 380 | O41: 388 | P41: 8 | Q41: Плюс | R41: 111.68 | S41: 195.44 | T41: 45972 | U41: Подадена | AE41: 45958 | AF41: 11 | AG41: MAGNUM TECHNOLOGY | AH41: MKEHAYOVA | AI41: SI25/B01/10/00008|BEAE42 | AN41: 30/10/2025 | AO41: 15903 | AP41: 7014
A42: B01 | B42: INTER CARS SA HSN TUNNEL | C42: VEN0001367 | D42: =IFERROR(HYPERLINK(INDEX(вендори!F:F,MATCH(C42,вендори!A:A,0)),INDEX(вендори!F:F,MATCH(C42,вендори!A:A,0))),"") -> ДАТА на дост.искат! | E42: 00000711/BLX/25/UE | F42: G119F5 | G42: EVMK0170 | H42: 711/BLX | I42: 00000711/BLX/25/UE | J42: 45943 | K42: EVMK0170 | L42: 0 | M42: 11.43 | N42: 3 | O42: 1 | P42: -2 | Q42: Минус | R42: -22.86 | S42: -44.710274 | T42: 45972 | U42: Анулирана | AC42: на 11.11. няма бройка в нот делив | AE42: 45947 | AF42: 18 | AG42: EVORON | AH42: SMILIEV | AI42: 00000711/BLX/25/UE|G119F5 | AN42: 30/10/2025 | AO42: 15876 | AP42: 6701
A43: B01 | B43: INTER CARS SA HSN TUNNEL | C43: VEN0001367 | D43: =IFERROR(HYPERLINK(INDEX(вендори!F:F,MATCH(C43,вендори!A:A,0)),INDEX(вендори!F:F,MATCH(C43,вендори!A:A,0))),"") -> ДАТА на дост.искат! | E43: 00000716/BLX/25/UE | F43: H06KN1 | G43: A41-1062-021 | H43: 716/BLX | I43: 00000716/BLX/25/UE | J43: 45945 | K43: A41-1062-021 | L43: 0 | M43: 14.56 | N43: 11 | O43: 7 | P43: -4 | Q43: Минус | R43: -58.24 | S43: -113.90754 | T43: 45972 | U43: Получено КИ | V43: 01740949/HZA/25/UEK | W43: 45980 | AE43: 45952 | AF43: 15 | AG43: ASPOCK | AH43: DEIVANOV | AI43: 00000716/BLX/25/UE|H06KN1 | AN43: 22/10/2025 | AO43: 15337 | AP43: 6845
A44: B01 | B44: INTER CARS SA HSN TUNNEL | C44: VEN0001367 | D44: =IFERROR(HYPERLINK(INDEX(вендори!F:F,MATCH(C44,вендори!A:A,0)),INDEX(вендори!F:F,MATCH(C44,вендори!A:A,0))),"") -> ДАТА на дост.искат! | E44: 00000716/BLX/25/UE | F44: H06KMY | G44: A41-1061-021 | H44: 716/BLX | I44: 00000716/BLX/25/UE | J44: 45945 | K44: A41-1061-021 | L44: 0 | M44: 12.63 | N44: 2 | O44: 0 | P44: -2 | Q44: Минус | R44: -25.26 | S44: -49.404266 | T44: 45972 | U44: Получено КИ | V44: 01740949/HZA/25/UEK | W44: 45980 | AE44: 45952 | AF44: 15 | AG44: ASPOCK | AH44: DEIVANOV | AI44: 00000716/BLX/25/UE|H06KMY | AN44: 22/10/2025 | AO44: 15336 | AP44: 6845
A45: B01 | B45: KYB EUROPE GMBH | C45: VEN0001241 | D45: =IFERROR(HYPERLINK(INDEX(вендори!F:F,MATCH(C45,вендори!A:A,0)),INDEX(вендори!F:F,MATCH(C45,вендори!A:A,0))),"") -> бланка | E45: 26INGE14611 | F45: A80A15 | G45: KYB334842 | H45: SA41463022 | I45: 26/INGE14611 | J45: 45945 | K45: 334842 | L45: 334842 | M45: 39.3 | N45: 6 | O45: 5 | P45: -1 | Q45: Минус | R45: -39.3 | S45: -76.864119 | T45: 45972 | U45: Отказани | AE45: 45958 | AF45: 11 | AG45: KAYABA | AH45: MKEHAYOVA | AI45: 26INGE14611|A80A15 | AN45: 29/10/2025 | AO45: 15847 | AP45: 7019
A46: B01 | B46: MANN HUMMEL GERMANY | C46: VEN0000533 | D46: =IFERROR(HYPERLINK(INDEX(вендори!F:F,MATCH(C46,вендори!A:A,0)),INDEX(вендори!F:F,MATCH(C46,вендори!A:A,0))),"") -> 0 | E46: 0101181760 | F46: G10X53 | G46: CUK 25 034-2 | H46: 24845587 | 0101181760 | I46: 0101181760 | J46: 45945 | K46: CUK 25 034-2 | L46: CUK 25 034-2 | M46: 30.3 | N46: 4 | O46: 3 | P46: -1 | Q46: Минус | R46: -30.3 | S46: -59.261649 | T46: 45972 | U46: Отказани | AE46: 45961 | AF46: 8 | AG46: MANN FILTER | AH46: VAPETROV | AI46: 0101181760|G10X53 | AN46: 45758 | AO46: 16148 | AP46: 7155
A47: B01 | B47: MANN HUMMEL GERMANY | C47: VEN0000533 | D47: =IFERROR(HYPERLINK(INDEX(вендори!F:F,MATCH(C47,вендори!A:A,0)),INDEX(вендори!F:F,MATCH(C47,вендори!A:A,0))),"") -> 0 | E47: 101185921 | F47: D06F15 | G47: WK 939/6 | I47: 0101185921 | J47: 45952 | K47: WK 939/6 | L47: WK 939/6 | M47: 13.1 | N47: 18 | O47: 16 | P47: -2 | Q47: Минус | R47: -26.2 | S47: -51.242746 | T47: 45972 | U47: Получено КИ | V47: 0101208588 | W47: 46001 | AE47: 45961 | AF47: 8 | AG47: MANN FILTER | AH47: VAPETROV | AI47: 101185921|D06F15 | AN47: 45758 | AO47: 16147 | AP47: 7172
A48: B01 | B48: MANN+HUMMEL FILTR. Sp. z o.o. | C48: VEN0000282 | D48: =IFERROR(HYPERLINK(INDEX(вендори!F:F,MATCH(C48,вендори!A:A,0)),INDEX(вендори!F:F,MATCH(C48,вендори!A:A,0))),"") -> 0 | E48: 25008308UF00001 | F48: D7380C | G48: K 1355 | H48: 25008308/UF/00001 | I48: 25008308/UF/00001 | J48: 45958 | K48: K 1355 | L48: K 1355 | M48: 2.7 | N48: 44 | O48: 26 | P48: -18 | Q48: Минус | R48: -48.6 | S48: -95.053338 | T48: 45972 | U48: Анулирана | AA48: 18 | AB48: 45987 | AC48: update sent | AD48: 45986 | AE48: 45962 | AF48: 7 | AG48: FILTRON | AH48: VAPETROV | AI48: 25008308UF00001|D7380C | AN48: 45849 | AO48: 16314 | AP48: 7181
A49: B01 | B49: MANN+HUMMEL FILTR. Sp. z o.o. | C49: VEN0000282 | D49: =IFERROR(HYPERLINK(INDEX(вендори!F:F,MATCH(C49,вендори!A:A,0)),INDEX(вендори!F:F,MATCH(C49,вендори!A:A,0))),"") -> 0 | E49: 25008308UF00001 | F49: A84191 | G49: PP 968/4 | H49: 25008308/UF/00001 | I49: 25008308/UF/00001 | J49: 45958 | K49: PP 968/4 | M49: 7,99 | N49: 0 | O49: 12 | P49: 12 | Q49: Плюс | R49: 95.88 | S49: 187.52498 | T49: 45972 | U49: Получено ДИ/фактура | V49: 25009679/UF/00001 | W49: 46006 | X49: 17.12.25 (през СМ не го намирам!) | AE49: 45962 | AF49: 7 | AI49: 25008308UF00001|A84191 | AN49: 45849 | AO49: 16312 | AP49: 7181
A50: B01 | B50: MARELLI AFTERMARKET POLAND Sp. z o.o. | C50: VEN0000375 | D50: =IFERROR(HYPERLINK(INDEX(вендори!F:F,MATCH(C50,вендори!A:A,0)),INDEX(вендори!F:F,MATCH(C50,вендори!A:A,0))),"") -> бланка | E50: 253007335 | F50: AAA0DA | G50: 941318111231 | H50: 96375103 | 0253007335 | I50: 0253007335 | J50: 45950 | K50: 941318111231 | L50: 941318111231 | M50: 3.1 | N50: 64 | O50: 74 | P50: 10 | Q50: Плюс | R50: 31 | S50: 60.63073 | T50: 45972 | U50: Получено ДИ/фактура | V50: 0263100093 | W50: 46049 | X50: 46065 | AE50: 45957 | AF50: 12 | AG50: MAGNETI MARELLI | AH50: KMINKOV | AI50: 253007335|AAA0DA | AN50: 28/10/2025 | AO50: 15795 | AP50: 6982
A51: B01 | B51: MARELLI AFTERMARKET POLAND Sp. z o.o. | C51: VEN0000375 | D51: =IFERROR(HYPERLINK(INDEX(вендори!F:F,MATCH(C51,вендори!A:A,0)),INDEX(вендори!F:F,MATCH(C51,вендори!A:A,0))),"") -> бланка | E51: 253007725 | F51: E12FD6 | H51: 96375900 | 0253007725 | I51: 0253007725 | J51: 45964 | K51: 215810006900 | L51: 215810006900 | M51: 40.29 | N51: 10 | O51: 0 | P51: -10 | Q51: Минус | R51: -402.9 | S51: -788.00391 | T51: 45972 | U51: Отказани | AE51: 45967 | AF51: 4 | AG51: MAGNETI MARELLI | AH51: KMINKOV | AI51: 253007725|E12FD6 | AN51: 45911 | AO51: 16385 | AP51: 7376
A52: B01 | B52: MEAT & DORIA SRL | C52: VEN0001959 | D52: =IFERROR(HYPERLINK(INDEX(вендори!F:F,MATCH(C52,вендори!A:A,0)),INDEX(вендори!F:F,MATCH(C52,вендори!A:A,0))),"") -> 0 | E52: 25130082 | F52: G05F19 | G52: MDK106093 | H52: 2513008 | I52: 2513008 /2 | J52: 45951 | K52: K106093 | M52: 18.72 | N52: 0 | O52: 2 | P52: 2 | Q52: Плюс | R52: 37.44 | S52: 73.226275 | T52: 45972 | U52: Получено ДИ/фактура | V52: 2514896 /2 | W52: 45987 | X52: CM 27.11.25 | AE52: 45971 | AF52: 2 | AI52: 25130082|G05F19 | AN52: 45941 | AO52: 16399 | AP52: 7116
A53: B01 | B53: MEAT & DORIA SRL | C53: VEN0001959 | D53: =IFERROR(HYPERLINK(INDEX(вендори!F:F,MATCH(C53,вендори!A:A,0)),INDEX(вендори!F:F,MATCH(C53,вендори!A:A,0))),"") -> 0 | E53: 25130082 | F53: F816DC | G53: MDK107062 | H53: 2513008 | I53: 2513008 /2 | J53: 45951 | K53: K107062 | M53: 14.32 | N53: 0 | O53: 3 | P53: 3 | Q53: Плюс | R53: 42.96 | S53: 84.022457 | T53: 45972 | U53: Получено ДИ/фактура | V53: 2514896 /2 | W53: 45987 | X53: CM 27.11.25 | AE53: 45971 | AF53: 2 | AI53: 25130082|F816DC | AN53: 45941 | AO53: 16401 | AP53: 7116
A54: B01 | B54: MEAT & DORIA SRL | C54: VEN0001959 | D54: =IFERROR(HYPERLINK(INDEX(вендори!F:F,MATCH(C54,вендори!A:A,0)),INDEX(вендори!F:F,MATCH(C54,вендори!A:A,0))),"") -> 0 | E54: 25130082 | F54: G05T0B | G54: MDK106023 | H54: 2513008 | I54: 2513008 /2 | J54: 45951 | K54: K106023 | M54: 11.13 | N54: 0 | O54: 4 | P54: 4 | Q54: Плюс | R54: 44.52 | S54: 87.073552 | T54: 45972 | U54: Получено ДИ/фактура | V54: 2514896 /2 | W54: 45987 | X54: CM 27.11.25 | AE54: 45971 | AF54: 2 | AI54: 25130082|G05T0B | AN54: 45941 | AO54: 16398 | AP54: 7116
A55: B01 | B55: MEAT & DORIA SRL | C55: VEN0001959 | D55: =IFERROR(HYPERLINK(INDEX(вендори!F:F,MATCH(C55,вендори!A:A,0)),INDEX(вендори!F:F,MATCH(C55,вендори!A:A,0))),"") -> 0 | E55: 25130082 | F55: F816D5 | G55: MDK107055 | H55: 2513008 | I55: 2513008 /2 | J55: 45951 | K55: K107055 | M55: 16.34 | N55: 0 | O55: 4 | P55: 4 | Q55: Плюс | R55: 65.36 | S55: 127.83305 | T55: 45972 | U55: Получено ДИ/фактура | V55: 2514896 /2 | W55: 45987 | X55: CM 27.11.25 | AE55: 45971 | AF55: 2 | AI55: 25130082|F816D5 | AN55: 45941 | AO55: 16397 | AP55: 7116
A56: B01 | B56: Moove Lubricants Limited | C56: VEN0000361 | D56: =IFERROR(HYPERLINK(INDEX(вендори!F:F,MATCH(C56,вендори!A:A,0)),INDEX(вендори!F:F,MATCH(C56,вендори!A:A,0))),"") -> 0 | E56: 9000205984 | F56: 9F03ED | G56: AQF ATF 5L | H56: 9000205984 | I56: 9000205984 | J56: 45951 | K56: ATF5L | L56: ATF5L | M56: 16.72 | N56: 4 | O56: 0 | P56: -4 | Q56: Минус | R56: -66.88 | S56: -130.80591 | T56: 45972 | U56: МАСЛА - обработва се от РМ | AE56: 45958 | AF56: 11 | AG56: COMMA | AH56: MDRINEV | AI56: 9000205984|9F03ED | AN56: 31/10/2025 | AO56: 15972 | AP56: 7011
A57: B01 | B57: Moove Lubricants Limited | C57: VEN0000361 | D57: =IFERROR(HYPERLINK(INDEX(вендори!F:F,MATCH(C57,вендори!A:A,0)),INDEX(вендори!F:F,MATCH(C57,вендори!A:A,0))),"") -> 0 | E57: 9000205984 | F57: F4C98D | G57: ECO-M 0W20 5L | H57: 9000205984 | I57: 9000205984 | K57: ECO-M 0W20 5L | N57: 0 | O57: 4 | P57: 4 | Q57: Плюс | R57: #VALUE! | S57: #VALUE! | T57: 45972 | U57: МАСЛА - обработва се от РМ | AE57: 45958 | AF57: 11 | AI57: 9000205984|F4C98D | AN57: 31/10/2025 | AO57: 15970 | AP57: 7011
A58: B01 | B58: Moove Lubricants Limited | C58: VEN0000361 | D58: =IFERROR(HYPERLINK(INDEX(вендори!F:F,MATCH(C58,вендори!A:A,0)),INDEX(вендори!F:F,MATCH(C58,вендори!A:A,0))),"") -> 0 | E58: 9000205984 | F58: 9F02B4 | G58: SX75W90 GL5 1L SEMIS. | H58: 9000205984 | I58: 9000205984 | J58: 45951 | K58: SX1L | L58: SX1L | M58: 5.12 | N58: 300 | O58: 324 | P58: 24 | Q58: Плюс | R58: 122.88 | S58: 240.33239 | T58: 45972 | U58: МАСЛА - обработва се от РМ | AE58: 45958 | AF58: 11 | AG58: COMMA | AH58: MDRINEV | AI58: 9000205984|9F02B4 | AN58: 31/10/2025 | AO58: 15971 | AP58: 7011
A59: B01 | B59: MOTUL DEUTSCHLAND GMBH | C59: VEN0001554 | D59: =IFERROR(HYPERLINK(INDEX(вендори!F:F,MATCH(C59,вендори!A:A,0)),INDEX(вендори!F:F,MATCH(C59,вендори!A:A,0))),"") -> 0 | E59: 550793975 | F59: G0TDT6 | G59: 8100 ECO-LITE OW16 5L | H59: 83735525 | I59: 550793975 | J59: 45954 | K59: 110379 | L59: 110379 | M59: 34.69 | N59: 4 | O59: 0 | P59: -4 | Q59: Минус | R59: -138.76 | S59: -271.39097 | T59: 45972 | U59: МАСЛА - обработва се от РМ | AE59: 45957 | AF59: 12 | AG59: MOTUL | AH59: MDRINEV | AI59: 550793975|G0TDT6 | AN59: 29/10/2025 | AO59: 15830 | AP59: 6989
A60: B01 | B60: MOTUL DEUTSCHLAND GMBH | C60: VEN0001554 | D60: =IFERROR(HYPERLINK(INDEX(вендори!F:F,MATCH(C60,вендори!A:A,0)),INDEX(вендори!F:F,MATCH(C60,вендори!A:A,0))),"") -> 0 | E60: 550793975 | F60: C42CDF | G60: OUTBOARD TECH 4T 10W405L | H60: 83735525 | I60: 550793975 | J60: 45954 | K60: 106354 | L60: 101750__106354 | M60: 18.76 | N60: 24 | O60: 32 | P60: 8 | Q60: Плюс | R60: 150.08 | S60: 293.53097 | T60: 45972 | U60: МАСЛА - обработва се от РМ | AE60: 45957 | AF60: 12 | AG60: MOTUL | AH60: MDRINEV | AI60: 550793975|C42CDF | AN60: 29/10/2025 | AO60: 15831 | AP60: 6989
A61: B01 | B61: MS MOTORSERVICE INTERNATIONAL GMBH | C61: VEN0001314 | D61: =IFERROR(HYPERLINK(INDEX(вендори!F:F,MATCH(C61,вендори!A:A,0)),INDEX(вендори!F:F,MATCH(C61,вендори!A:A,0))),"") -> 0 | E61: 2430417934 | F61: F8EDE1 | G61: 7.07919.15.0 | H61: 80795800 | I61: 2430417934 | J61: 45945 | K61: 7.07919.15.0 | L61: 7.07919.15.0 | M61: 74.93 | N61: 4 | O61: 3 | P61: -1 | Q61: Минус | R61: -74.93 | S61: -146.55034 | T61: 45972 | U61: Получено КИ | V61: 2431082558 | W61: 45978 | AE61: 45950 | AF61: 17 | AG61: PIERBURG | AH61: AGEORGIEV | AI61: 2430417934|F8EDE1 | AN61: 29/10/2025 | AO61: 15807 | AP61: 6764
A62: B01 | B62: MS MOTORSERVICE INTERNATIONAL GMBH | C62: VEN0001314 | D62: =IFERROR(HYPERLINK(INDEX(вендори!F:F,MATCH(C62,вендори!A:A,0)),INDEX(вендори!F:F,MATCH(C62,вендори!A:A,0))),"") -> 0 | E62: 2430418229 | F62: B37D6B | G62: 20 1003 50101 | H62: 80795894 | I62: 2430418229 | J62: 45947 | K62: 20100350101 | L62: 20100350101 | M62: 549.64 | N62: 1 | O62: 0 | P62: -1 | Q62: Минус | R62: -549.64 | S62: -1075.0024 | T62: 45972 | U62: Получено КИ | V62: 2431082559 + ДИ 2430423058/03.12.25 | W62: 45978 | AA62: 1 | AB62: 45982 | AC62: поискано дебитно - ок | AD62: 45981 | AE62: 45959 | AF62: 10 | AG62: BF | AH62: AGEORGIEV | AI62: 2430418229|B37D6B | AN62: 45849 | AO62: 16247 | AP62: 7067
A63: B01 | B63: MS MOTORSERVICE INTERNATIONAL GMBH | C63: VEN0001314 | D63: =IFERROR(HYPERLINK(INDEX(вендори!F:F,MATCH(C63,вендори!A:A,0)),INDEX(вендори!F:F,MATCH(C63,вендори!A:A,0))),"") -> 0 | E63: 2430419197 | F63: F4F42E | G63: 7.24808.27.0 | H63: 80797586 | I63: 2430419197 | J63: 45958 | K63: 7.24808.27.0 | M63: 166.11 | N63: 0 | O63: 11 | P63: 11 | Q63: Плюс | R63: 1827.21 | S63: 3573.7121 | T63: 45972 | U63: Получено ДИ/фактура | V63: 2430421527 | W63: 45975 | X63: CM 24.11.25 | AE63: 45959 | AF63: 10 | AI63: 2430419197|F4F442E | AN63: 45880 | AO63: 16374 | AP63: 7341
A64: B01 | B64: MS MOTORSERVICE INTERNATIONAL GMBH | C64: VEN0001314 | D64: =IFERROR(HYPERLINK(INDEX(вендори!F:F,MATCH(C64,вендори!A:A,0)),INDEX(вендори!F:F,MATCH(C64,вендори!A:A,0))),"") -> 0 | E64: 2430419625 | F64: D19C9B | G64: 7.02552.44.0 | H64: 80797590 | I64: 2430419625 | J64: 45961 | K64: 7.02552.44.0 | L64: 7.02552.44.0 | M64: 59.75 | N64: 1 | O64: 2 | P64: 1 | Q64: Плюс | R64: 59.75 | S64: 116.86084 | T64: 45972 | U64: Получено ДИ/фактура | V64: 2430421526 | W64: 45975 | X64: CM 24.11.25 | AE64: 45968 | AF64: 3 | AG64: PIERBURG | AH64: KMINKOV | AI64: 2430419625|D19C9B | AN64: 45941 | AO64: 16407 | AP64: 7397
A65: B01 | B65: MS MOTORSERVICE INTERNATIONAL GMBH | C65: VEN0001314 | D65: =IFERROR(HYPERLINK(INDEX(вендори!F:F,MATCH(C65,вендори!A:A,0)),INDEX(вендори!F:F,MATCH(C65,вендори!A:A,0))),"") -> 0 | E65: 2430419625 | F65: C3F359 | G65: 7.02701.79.01 | H65: 80797590 | I65: 2430419625 | J65: 45961 | K65: 7.02701.79.0 | L65: 7.02701.79.0 | M65: 78.49 | N65: 1 | O65: 2 | P65: 1 | Q65: Плюс | R65: 78.49 | S65: 153.5131 | T65: 45972 | U65: Получено ДИ/фактура | V65: 2430421526 | W65: 45975 | X65: CM 24.11.25 | AE65: 45968 | AF65: 3 | AG65: PIERBURG | AH65: KMINKOV | AI65: 2430419625|C3F359 | AN65: 45941 | AO65: 16408 | AP65: 7397
A66: B01 | B66: Niterra EMEA GmbH | C66: VEN0001353 | D66: =IFERROR(HYPERLINK(INDEX(вендори!F:F,MATCH(C66,вендори!A:A,0)),INDEX(вендори!F:F,MATCH(C66,вендори!A:A,0))),"") -> 0 | E66: 32522437 | F66: D4A5C8 | G66: NGK48410 | H66: 82740224 | I66: 32522437 | J66: 45950 | K66: 48410 | L66: 48410 | M66: 27.74 | N66: 10 | O66: 9 | P66: -1 | Q66: Минус | R66: -27.74 | S66: -54.254724 | T66: 45972 | U66: Получено КИ | V66: 39195371 | W66: 45975 | AE66: 45960 | AF66: 9 | AG66: NGK | AH66: KMINKOV | AI66: 32522437|D4A5C8 | AN66: 31/10/2025 | AO66: 15946 | AP66: 7137
A67: B01 | B67: NRF POLAND Sp.z o.o. | C67: VEN0000736 | D67: =IFERROR(HYPERLINK(INDEX(вендори!F:F,MATCH(C67,вендори!A:A,0)),INDEX(вендори!F:F,MATCH(C67,вендори!A:A,0))),"") -> 0 | E67: SI123983 | F67: C3FF20 | G67: NRF 539564 | H67: SI-123983 | SI-123984 | I67: SI-123983 | J67: 45929 | K67: 539564 | L67: 539564 | M67: 234.59 | N67: 1 | O67: 0 | P67: -1 | Q67: Минус | R67: -234.59 | S67: -458.81816 | T67: 45972 | U67: Подадена | AE67: 45936 | AF67: 27 | AG67: NRF | AH67: KMINKOV | AI67: SI123983|C3FF20 | AN67: 45849 | AO67: 16277 | AP67: 6272
A68: B01 | B68: NRF POLAND Sp.z o.o. | C68: VEN0000736 | D68: =IFERROR(HYPERLINK(INDEX(вендори!F:F,MATCH(C68,вендори!A:A,0)),INDEX(вендори!F:F,MATCH(C68,вендори!A:A,0))),"") -> 0 | E68: SI123984 | F68: AE5895 | G68: NRF 58198 | H68: SI-123983 | SI-123984 | I68: SI-123984 | J68: 45929 | K68: 58198 | L68: 58198 | M68: 26.92 | N68: 10 | O68: 0 | P68: -10 | Q68: Минус | R68: -269.2 | S68: -526.50944 | T68: 45972 | U68: Подадена | AE68: 45936 | AF68: 27 | AG68: NRF | AH68: KMINKOV | AI68: SI123984|AE5895 | AN68: 45849 | AO68: 16262 | AP68: 6272
A69: B01 | B69: NRF POLAND Sp.z o.o. | C69: VEN0000736 | D69: =IFERROR(HYPERLINK(INDEX(вендори!F:F,MATCH(C69,вендори!A:A,0)),INDEX(вендори!F:F,MATCH(C69,вендори!A:A,0))),"") -> 0 | F69: BA57A9 | G69: NRF 55348 | H69: SI-123983 | SI-123984 | I69: SI-123984 | J69: 45929 | K69: 55348 | L69: 55348 | M69: 89.56 | N69: 9 | O69: 3 | P69: -6 | Q69: Минус | R69: -537.36 | S69: -1050.9848 | T69: 45972 | U69: Подадена | AE69: 45936 | AF69: 27 | AG69: NRF | AH69: KMINKOV | AI69: SI123984|BA57A9 | AN69: 45849 | AO69: 16263 | AP69: 6272
A70: B01 | B70: NRF POLAND Sp.z o.o. | C70: VEN0000736 | D70: =IFERROR(HYPERLINK(INDEX(вендори!F:F,MATCH(C70,вендори!A:A,0)),INDEX(вендори!F:F,MATCH(C70,вендори!A:A,0))),"") -> 0 | E70: SI123984 | F70: C3CA25 | G70: NRF 53831 | H70: SI-123983 | SI-123984 | I70: SI-123984 | J70: 45929 | K70: 53831 | L70: 53831 | M70: 55.39 | N70: 4 | O70: 0 | P70: -4 | Q70: Минус | R70: -221.56 | S70: -433.33369 | T70: 45972 | U70: Подадена | AE70: 45936 | AF70: 27 | AG70: NRF | AH70: KMINKOV | AI70: SI123984|C3CA25 | AN70: 45849 | AO70: 16261 | AP70: 6272
A71: B01 | B71: NRF POLAND Sp.z o.o. | C71: VEN0000736 | D71: =IFERROR(HYPERLINK(INDEX(вендори!F:F,MATCH(C71,вендори!A:A,0)),INDEX(вендори!F:F,MATCH(C71,вендори!A:A,0))),"") -> 0 | E71: SI123984 | F71: AE5807 | G71: NRF 55327 | H71: SI-123983 | SI-123984 | I71: SI-123984 | J71: 45929 | K71: 55327 | L71: 55327 | M71: 37.84 | N71: 7 | O71: 5 | P71: -2 | Q71: Минус | R71: -75.68 | S71: -148.01721 | T71: 45972 | U71: Подадена | AE71: 45936 | AF71: 27 | AG71: NRF | AH71: KMINKOV | AI71: SI123984|AE5807 | AN71: 45849 | AO71: 16264 | AP71: 6272
A72: B01 | B72: OE Germany GmbH | C72: VEN0003333 | D72: =IFERROR(HYPERLINK(INDEX(вендори!F:F,MATCH(C72,вендори!A:A,0)),INDEX(вендори!F:F,MATCH(C72,вендори!A:A,0))),"") -> 0 | E72: VRG0075425 | F72: E5D947 | G72: 01 0300 651001 | H72: VRG0075425 | I72: VRG0075425 | J72: 45943 | K72: 01 0300 651001 | L72: 0 | M72: 560 | N72: 1 | O72: 0 | P72: -1 | Q72: Минус | R72: -560 | S72: -1095.2648 | T72: 45972 | U72: Подадена | AE72: 45953 | AF72: 14 | AG72: OE GERMANY | AH72: AGEORGIEV | AI72: VRG0075425|E5D947 | AN72: 27/10/2025 | AO72: 15706 | AP72: 6911
A73: B01 | B73: PE AUTOMOTIVE GmbH & Co. KG | C73: VEN0002164 | D73: =IFERROR(HYPERLINK(INDEX(вендори!F:F,MATCH(C73,вендори!A:A,0)),INDEX(вендори!F:F,MATCH(C73,вендори!A:A,0))),"") -> 0 | E73: INDE1700007486 | F73: E29975 | G73: 143.604-00 | H73: INDE1700007486 | I73: INDE1700007486 | J73: 45922 | K73: 143.604-00A | L73: 143.604-00A | M73: 46.5 | N73: 8 | O73: 7 | P73: -1 | Q73: Минус | R73: -46.5 | S73: -90.946095 | T73: 45972 | U73: Получено КИ | V73: CRDE1700002713 | W73: 45975 | AE73: 45932 | AF73: 29 | AG73: PETERS | AH73: DPETARNISHKA | AI73: INDE1700007486|E29975 | AN73: 31/10/2025 | AO73: 15935 | AP73: 6201
A74: B01 | B74: PHINIA DELPHI UK Ltd. | C74: VEN0001138 | D74: =IFERROR(HYPERLINK(INDEX(вендори!F:F,MATCH(C74,вендори!A:A,0)),INDEX(вендори!F:F,MATCH(C74,вендори!A:A,0))),"") -> бланка | E74: 8247057701 | F74: H0VVKP | G74: TEM133 | H74: 80361945 | 80364831 | 80367499 | 80369386 | 80374386 | 80376482 | 80376802 | I74: 8247057701 | J74: 45944 | K74: TEM133 | L74: TEM133 | M74: 35.99 | N74: 3 | O74: 1 | P74: -2 | Q74: Минус | R74: -71.98 | S74: -140.78064 | T74: 45972 | U74: Анулирана | AA74: 2 | AB74: ок | AC74: преди подаване | AD74: 45973 | AE74: 45950 | AF74: 17 | AG74: DELPHI | AH74: AGEORGIEV | AI74: 8247057701|H0VVKP | AN74: 29/10/2025 | AO74: 15869 | AP74: 6777
A75: B01 | B75: PHINIA DELPHI UK Ltd. | C75: VEN0001138 | D75: =IFERROR(HYPERLINK(INDEX(вендори!F:F,MATCH(C75,вендори!A:A,0)),INDEX(вендори!F:F,MATCH(C75,вендори!A:A,0))),"") -> бланка | E75: 8247057701 | F75: E618E0 | G75: TC3436 | H75: 80361945 | 80364831 | 80367499 | 80369386 | 80374386 | 80376482 | 80376802 | I75: 8247057701 | J75: 45944 | K75: TC3436 | L75: TC3436 | M75: 41.7 | N75: 1 | O75: 0 | P75: -1 | Q75: Минус | R75: -41.7 | S75: -81.558111 | T75: 45972 | U75: Анулирана | AA75: 1 | AB75: ок | AC75: преди подаване | AD75: 45973 | AE75: 45950 | AF75: 17 | AG75: DELPHI | AH75: KDOBREV | AI75: 8247057701|E618E0 | AN75: 29/10/2025 | AO75: 15868 | AP75: 6777
A76: B01 | B76: ROBERT BOSCH SRL | C76: VEN0000779 | D76: =IFERROR(HYPERLINK(INDEX(вендори!F:F,MATCH(C76,вендори!A:A,0)),INDEX(вендори!F:F,MATCH(C76,вендори!A:A,0))),"") -> деливъри задължително | E76: 2045253201 | F76: 535309 | G76: 0 986 424 364 | H76: Деливъри 8151621431 , последните цифри - EKA | I76: 2045253201 | J76: 45943 | K76: 0.986.424.364.EKA | L76: 0.986.424.364 | M76: 23.13 | N76: 42 | O76: 46 | P76: 4 | Q76: Плюс | R76: 92.52 | S76: 92.52 | T76: 45972 | U76: Отказани | AE76: 45945 | AF76: 20 | AG76: BOSCH | AH76: KDOBREV | AI76: 2045253201|535309 | AN76: 28/10/2025 | AO76: 15786 | AP76: 6609
A77: B01 | B77: ROBERT BOSCH SRL | C77: VEN0000779 | D77: =IFERROR(HYPERLINK(INDEX(вендори!F:F,MATCH(C77,вендори!A:A,0)),INDEX(вендори!F:F,MATCH(C77,вендори!A:A,0))),"") -> деливъри задължително | E77: 2045253202 | F77: G0R39W | H77: Деливъри 8151621432 | I77: 2045253202 | J77: 45943 | K77: 3.579.671.105.002 | L77: 3.579.671.105 | M77: 216 | N77: 4 | O77: 2 | P77: -2 | Q77: Минус | R77: -432 | S77: -432 | T77: 45972 | U77: Получено КИ | V77: 2045256822 | W77: 45986 | AE77: 45945 | AF77: 20 | AG77: BOSCH | AH77: KMINKOV | AI77: 2045253202|G0R39W | AN77: 29/10/2025 | AO77: 15829 | AP77: 6609
A78: B01 | B78: ROBERT BOSCH SRL | C78: VEN0000779 | D78: =IFERROR(HYPERLINK(INDEX(вендори!F:F,MATCH(C78,вендори!A:A,0)),INDEX(вендори!F:F,MATCH(C78,вендори!A:A,0))),"") -> деливъри задължително | E78: 2045254217 | F78: C2E73B | G78: 0 986 435 150 | H78: 824727651 | I78: 2045254217 | J78: 45954 | K78: 0.986.435.150.952 | L78: 0.986.435.150 | M78: 288,29 | N78: 10 | O78: 7 | P78: -3 | Q78: Минус | R78: -864.87 | S78: -864.87 | T78: 45972 | U78: Получено КИ | V78: 2045256820 | W78: 45986 | AE78: 45965 | AF78: 6 | AG78: BOSCH | AH78: KMINKOV | AI78: 2045254217|C2E73B | AN78: 45788 | AO78: 16198 | AP78: 7263
A79: B01 | B79: ROBERT BOSCH SRL | C79: VEN0000779 | D79: =IFERROR(HYPERLINK(INDEX(вендори!F:F,MATCH(C79,вендори!A:A,0)),INDEX(вендори!F:F,MATCH(C79,вендори!A:A,0))),"") -> деливъри задължително | E79: 2045254532 | F79: C2F4F4 | G79: F 026 400 119 | H79: 8151628300 | I79: 2045254532 | J79: 45959 | K79: F.026.400.119.HWS | M79: 23,8 | N79: 45 | O79: 25 | P79: -20 | Q79: Минус | R79: -476 | S79: -476 | T79: 45972 | U79: Отказани | AE79: 45965 | AF79: 6 | AI79: 2045254533|C2F4F4 | AN79: 45819 | AO79: 16237 | AP79: 7154
A80: B01 | B80: ROBERT BOSCH SRL | C80: VEN0000779 | D80: =IFERROR(HYPERLINK(INDEX(вендори!F:F,MATCH(C80,вендори!A:A,0)),INDEX(вендори!F:F,MATCH(C80,вендори!A:A,0))),"") -> деливъри задължително | E80: 2045254533 | F80: DD6ACC | G80: F 026 407 142 | H80: 8151628301 | I80: 2045254533 | J80: 45959 | K80: F.026.407.142.HWS | L80: F.026.407.142 | M80: 5.13 | N80: 40 | O80: 10 | P80: -30 | Q80: Минус | R80: -153.9 | S80: -153.9 | T80: 45972 | U80: Получено КИ | V80: 2045256823 | W80: 45986 | AE80: 45961 | AF80: 8 | AG80: BOSCH | AH80: VAPETROV | AI80: 2045254533|DD6ACC | AN80: 45819 | AO80: 16236 | AP80: 7154
A81: B01 | B81: ROBERT BOSCH SRL | C81: VEN0000779 | D81: =IFERROR(HYPERLINK(INDEX(вендори!F:F,MATCH(C81,вендори!A:A,0)),INDEX(вендори!F:F,MATCH(C81,вендори!A:A,0))),"") -> деливъри задължително | E81: 2045254533 | F81: 478577 | G81: 0 450 906 322 | H81: 8151628301 | I81: 2045254533 | J81: 45959 | K81: 0.450.906.322.HWS | M81: 20,34 | N81: 10 | O81: 20 | P81: 10 | Q81: Плюс | R81: 203.4 | S81: 203.4 | T81: 45972 | U81: Отказани | AE81: 45961 | AF81: 8 | AI81: 2045254532|478577 | AN81: 45788 | AO81: 16158 | AP81: 7154
A82: B01 | B82: S.A.S.I.C. - S.A.SANTUCCI SICFA REUNIS | C82: VEN0001290 | D82: =IFERROR(HYPERLINK(INDEX(вендори!F:F,MATCH(C82,вендори!A:A,0)),INDEX(вендори!F:F,MATCH(C82,вендори!A:A,0))),"") -> 0 | E82: FAS202502442 | F82: DDBC37 | G82: SAS3654008 | H82: FAS-2025/02442 | I82: FAS-2025/02442 | J82: 45953 | K82: 3654008 | L82: 3654008 | M82: 31.87 | N82: 2 | O82: 0 | P82: -2 | Q82: Минус | R82: -63.74 | S82: -124.6646 | T82: 45972 | U82: Получено КИ | V82: FSK-2025/02619 | W82: 45979 | AC82: били са отказани | AE82: 45966 | AF82: 5 | AG82: SASIC | AH82: AGEORGIEV | AI82: FAS202502442|DDBC37 | AN82: 45849 | AO82: 16296 | AP82: 7290
A83: B01 | B83: S.A.S.I.C. - S.A.SANTUCCI SICFA REUNIS | C83: VEN0001290 | D83: =IFERROR(HYPERLINK(INDEX(вендори!F:F,MATCH(C83,вендори!A:A,0)),INDEX(вендори!F:F,MATCH(C83,вендори!A:A,0))),"") -> 0 | E83: FAS202502442 | F83: E2D699 | G83: SAS3650008 | H83: FAS-2025/02442 | I83: FAS-2025/02442 | J83: 45953 | K83: 3650008 | M83: 48.76 | N83: 0 | O83: 2 | P83: 2 | Q83: Плюс | R83: 97.52 | S83: 190.73254 | T83: 45972 | U83: Получено ДИ/фактура | V83: FAS-2025/02620 | W83: 45979 | X83: CM 24.11.25 | AE83: 45966 | AF83: 5 | AI83: FAS202502442|E2D699 | AN83: 45849 | AO83: 16297 | AP83: 7290
A84: B01 | B84: Schaeffler Vehicle Lifetime SolutionsGermany GmbH | C84: VEN0000463 | D84: =IFERROR(HYPERLINK(INDEX(вендори!F:F,MATCH(C84,вендори!A:A,0)),INDEX(вендори!F:F,MATCH(C84,вендори!A:A,0))),"") -> 0 | E84: 423581996 | F84: C34774 | G84: 370 0032 10 | H84: 61850388 | 61850389 | 61850390 | I84: 423581996 | J84: 45938 | K84: 3700032100 | M84: 238.53 | N84: 0 | O84: 0 | P84: 2 | Q84: Плюс | R84: 477.06 | S84: 933.04826 | T84: 45972 | U84: Получено ДИ/фактура | V84: 423598786 | W84: 45974 | X84: CM 24.11.25 | AE84: 45947 | AF84: 18 | AI84: 423581996|C34774 | AN84: 45788 | AO84: 16168 | AP84: 6711
A85: B01 | B85: Schaeffler Vehicle Lifetime SolutionsGermany GmbH | C85: VEN0000463 | D85: =IFERROR(HYPERLINK(INDEX(вендори!F:F,MATCH(C85,вендори!A:A,0)),INDEX(вендори!F:F,MATCH(C85,вендори!A:A,0))),"") -> 0 | E85: 423582070 | F85: B4AD14 | G85: 624 3224 34 | H85: 61850388 | 61850389 | 61850390 | I85: 423582070 | J85: 45938 | K85: 6243224340 | L85: 6243224340 | M85: 156.78 | N85: 3 | O85: 2 | P85: -1 | Q85: Минус | R85: -156.78 | S85: -306.63503 | T85: 45972 | U85: Отказани | AE85: 45947 | AF85: 18 | AG85: LUK | AH85: AGEORGIEV | AI85: 423582070|B4AD14 | AN85: 45788 | AO85: 16169 | AP85: 6711
A86: B01 | B86: Schaeffler Vehicle Lifetime SolutionsGermany GmbH | C86: VEN0000463 | D86: =IFERROR(HYPERLINK(INDEX(вендори!F:F,MATCH(C86,вендори!A:A,0)),INDEX(вендори!F:F,MATCH(C86,вендори!A:A,0))),"") -> 0 | E86: 423591800 | F86: C57572 | G86: 713 6495 60 | H86: 61898436 | 61898380 | 61898395 | I86: 423591800 | J86: 45959 | K86: 7136495600 | L86: 7136495600 | M86: 53.49 | N86: 3 | O86: 0 | P86: -3 | Q86: Минус | R86: -160.47 | S86: -313.85204 | T86: 45972 | U86: Отказани | AE86: 45962 | AF86: 7 | AG86: FAG | AH86: MKEHAYOVA | AI86: 423591800|C57572 | AN86: 45758 | AO86: 16121 | AP86: 7182
A87: B01 | B87: Schaeffler Vehicle Lifetime SolutionsGermany GmbH | C87: VEN0000463 | D87: =IFERROR(HYPERLINK(INDEX(вендори!F:F,MATCH(C87,вендори!A:A,0)),INDEX(вендори!F:F,MATCH(C87,вендори!A:A,0))),"") -> 0 | E87: 423591800 | F87: G0LPZC | G87: 529 0466 20 | H87: 61898436 | 61898380 | 61898395 | I87: 423591800 | J87: 45959 | K87: 5290466200 | L87: 5290466200 | M87: 31.05 | N87: 3 | O87: 2 | P87: -1 | Q87: Минус | R87: -31.05 | S87: -60.728521 | T87: 45972 | U87: Отказани | AE87: 45962 | AF87: 7 | AG87: INA | AH87: VAPETROV | AI87: 423591800|G0LPZC | AN87: 45758 | AO87: 16122 | AP87: 7182
A88: B01 | B88: Schaeffler Vehicle Lifetime SolutionsGermany GmbH | C88: VEN0000463 | D88: =IFERROR(HYPERLINK(INDEX(вендори!F:F,MATCH(C88,вендори!A:A,0)),INDEX(вендори!F:F,MATCH(C88,вендори!A:A,0))),"") -> 0 | E88: 423591800 | F88: G0OQVX | G88: 530 0742 30 | H88: 61898436 | 61898380 | 61898395 | I88: 423591800 | J88: 45959 | K88: 5300742300 | L88: 5300742300 | M88: 84.09 | N88: 1 | O88: 0 | P88: -1 | Q88: Минус | R88: -84.09 | S88: -164.46574 | T88: 45972 | U88: Анулирана | AA88: 1 | AB88: ок | AC88: ок, преди подаване | AD88: 45972 | AE88: 45962 | AF88: 7 | AG88: INA | AH88: VAPETROV | AI88: 423591800|G0OQVX | AN88: 45758 | AO88: 16123 | AP88: 7182
A89: B01 | B89: Schaeffler Vehicle Lifetime SolutionsGermany GmbH | C89: VEN0000463 | D89: =IFERROR(HYPERLINK(INDEX(вендори!F:F,MATCH(C89,вендори!A:A,0)),INDEX(вендори!F:F,MATCH(C89,вендори!A:A,0))),"") -> 0 | E89: 423591800 | F89: AFF4AE | G89: 713 6106 10 | H89: 61898436 | 61898380 | 61898395 | I89: 423591800 | J89: 45959 | K89: 713610610 | M89: 35.95 | N89: 0 | O89: 1 | P89: 1 | Q89: Плюс | R89: 35.95 | S89: 70.312089 | T89: 45972 | U89: Отказани | AE89: 45962 | AF89: 7 | AI89: 423591800|AFF4AE | AN89: 45758 | AO89: 16145 | AP89: 7182
A90: B01 | B90: TMD FRICTION SERVICES GmbH | C90: VEN0001592 | D90: =IFERROR(HYPERLINK(INDEX(вендори!F:F,MATCH(C90,вендори!A:A,0)),INDEX(вендори!F:F,MATCH(C90,вендори!A:A,0))),"") -> 0 | E90: 91818462 | F90: AF5F2C | G90: 2358501 | H90: 83004391 | I90: 91818462 | J90: 45936 | K90: 2358501 | L90: 2358501 | M90: 17.72 | N90: 6 | O90: 4 | P90: -2 | Q90: Минус | R90: -35.44 | S90: -69.314615 | T90: 45972 | U90: Получено КИ | V90: 91826438 | W90: 45982 | AE90: 45946 | AF90: 19 | AG90: TEXTAR | AH90: KDOBREV | AI90: 91818462|AF5F2C | AN90: 45880 | AO90: 16348 | AP90: 6659
A91: B01 | B91: TMD FRICTION SERVICES GmbH | C91: VEN0001592 | D91: =IFERROR(HYPERLINK(INDEX(вендори!F:F,MATCH(C91,вендори!A:A,0)),INDEX(вендори!F:F,MATCH(C91,вендори!A:A,0))),"") -> 0 | E91: 91818462 | F91: BEA8D6 | G91: 92184405 | H91: 83004391 | I91: 91818462 | J91: 45936 | K91: 92184405 | L91: 92184405 | M91: 28.91 | N91: 12 | O91: 11 | P91: -1 | Q91: Минус | R91: -28.91 | S91: -56.543045 | T91: 45972 | U91: Получено КИ | V91: 91826438 | W91: 45982 | AE91: 45946 | AF91: 19 | AG91: TEXTAR | AH91: KDOBREV | AI91: 91818462|BEA8D6 | AN91: 45880 | AO91: 16349 | AP91: 6659
A92: B01 | B92: TMD FRICTION SERVICES GmbH | C92: VEN0001592 | D92: =IFERROR(HYPERLINK(INDEX(вендори!F:F,MATCH(C92,вендори!A:A,0)),INDEX(вендори!F:F,MATCH(C92,вендори!A:A,0))),"") -> 0 | E92: 91818462 | F92: BEA719 | G92: 2439901 | H92: 83004391 | I92: 91818462 | J92: 45936 | K92: 2439901 | L92: 2439901 | M92: 30.27 | N92: 3 | O92: 5 | P92: 2 | Q92: Плюс | R92: 60.54 | S92: 118.40595 | T92: 45972 | U92: Получено ДИ/фактура | V92: 91825823 | W92: 45981 | X92: CM 26.11.25 | AE92: 45946 | AF92: 19 | AG92: TEXTAR | AH92: KDOBREV | AI92: 91818462|BEA719 | AN92: 45880 | AO92: 16352 | AP92: 6659
A93: B01 | B93: TMD FRICTION SERVICES GmbH | C93: VEN0001592 | D93: =IFERROR(HYPERLINK(INDEX(вендори!F:F,MATCH(C93,вендори!A:A,0)),INDEX(вендори!F:F,MATCH(C93,вендори!A:A,0))),"") -> 0 | E93: 91818462 | F93: B3AD09 | G93: 2453801 | H93: 83004391 | I93: 91818462 | J93: 45936 | K93: 2453801 | L93: 2453801 | M93: 19.93 | N93: 11 | O93: 13 | P93: 2 | Q93: Плюс | R93: 39.86 | S93: 77.959384 | T93: 45972 | U93: Получено ДИ/фактура | V93: 91825823 | W93: 45981 | X93: CM 26.11.25 | AE93: 45946 | AF93: 19 | AG93: TEXTAR | AH93: KDOBREV | AI93: 91818462|B3AD09 | AN93: 45880 | AO93: 16351 | AP93: 6659
A94: B01 | B94: TOMEX BRAKES SP. Z O.O. SP.K. | C94: VEN0001256 | D94: =IFERROR(HYPERLINK(INDEX(вендори!F:F,MATCH(C94,вендори!A:A,0)),INDEX(вендори!F:F,MATCH(C94,вендори!A:A,0))),"") -> 0 | E94: FSE44025 | F94: B4CE0B | G94: C1F031ABE | H94: FSE-440/25 | I94: FSE-440/25 | J94: 45952 | K94: C1F031ABE | L94: C1F031ABE | M94: 32.91 | N94: 11 | O94: 7 | P94: -4 | Q94: Минус | R94: -131.64 | S94: -63.1872 | T94: 45972 | U94: Получено КИ | V94: (S)FKE-477/25 | W94: 45979 | AE94: 45966 | AF94: 5 | AG94: ABE | AH94: KDOBREV | AI94: FSE44025|B4CE0B | AN94: 45849 | AO94: 16306 | AP94: 7293
A95: B01 | B95: TOMEX BRAKES SP. Z O.O. SP.K. | C95: VEN0001256 | D95: =IFERROR(HYPERLINK(INDEX(вендори!F:F,MATCH(C95,вендори!A:A,0)),INDEX(вендори!F:F,MATCH(C95,вендори!A:A,0))),"") -> 0 | E95: FSE44025 | F95: E57A87 | G95: C1R052ABE | H95: FSE-440/25 | I95: FSE-440/25 | J95: 45952 | K95: C1R052ABE | M95: 55 | N95: 0 | O95: 2 | P95: 2 | Q95: Плюс | R95: 110 | S95: 52.8 | T95: 45972 | U95: Получено ДИ/фактура | V95: (S)FSE-478/25 | W95: 45979 | X95: CM 24.11.25 | AE95: 45966 | AF95: 5 | AI95: FSE44025|E57A87 | AN95: 45849 | AO95: 16305 | AP95: 7293
A96: B01 | B96: TYC EUROPE B.V. | C96: VEN0002107 | D96: =IFERROR(HYPERLINK(INDEX(вендори!F:F,MATCH(C96,вендори!A:A,0)),INDEX(вендори!F:F,MATCH(C96,вендори!A:A,0))),"") -> бланка | E96: 5771141 | F96: D23E69 | G96: TYC 20-12748-15-2 | H96: MRSU6171795 | I96: 5771141 | J96: 45869 | K96: 20-12748-15-2 | L96: 20-12748-15-2__20-12748-15-2 | M96: 37.93 | N96: 4 | O96: 2 | P96: -2 | Q96: Минус | R96: -75.86 | S96: -148.36926 | T96: 45972 | U96: Подадена | AA96: 2 | AB96: 45981 | AC96: cancelled | AD96: 45980 | AE96: 45960 | AF96: 9 | AG96: TYC | AH96: DEIVANOV | AI96: 5771141|D23E69 | AN96: 31/10/2025 | AO96: 15959 | AP96: 7103
A97: B01 | B97: TYC EUROPE B.V. | C97: VEN0002107 | D97: =IFERROR(HYPERLINK(INDEX(вендори!F:F,MATCH(C97,вендори!A:A,0)),INDEX(вендори!F:F,MATCH(C97,вендори!A:A,0))),"") -> бланка | E97: 5773058 | F97: A9465B | G97: TYC 19-5081-05-2 | H97: MRSU5298738 | I97: 5773058 | J97: 45961 | K97: 19-5081-05-2 | L97: 19-5081-05-2__19-5081-05-2 | M97: 10.42 | N97: 9 | O97: 0 | P97: -9 | Q97: Минус | R97: -93.78 | S97: -183.41774 | T97: 45972 | U97: Подадена | AE97: 45961 | AF97: 8 | AG97: TYC | AH97: DEIVANOV | AI97: 5773058|A9465B | AN97: 45668 | AO97: 16005 | AP97: 7167
A98: B01 | B98: TYC EUROPE B.V. | C98: VEN0002107 | D98: =IFERROR(HYPERLINK(INDEX(вендори!F:F,MATCH(C98,вендори!A:A,0)),INDEX(вендори!F:F,MATCH(C98,вендори!A:A,0))),"") -> бланка | E98: 5773058 | F98: B440E6 | G98: TYC 19-0102-05-2 | H98: MRSU5298738 | I98: 5773058 | J98: 45961 | K98: 19-0102-05-2 | L98: 19-0102-05-2__19-0102-05-2 | M98: 8.99 | N98: 5 | O98: 0 | P98: -5 | Q98: Минус | R98: -44.95 | S98: -87.914558 | T98: 45972 | U98: Подадена | AE98: 45961 | AF98: 8 | AG98: TYC | AH98: DEIVANOV | AI98: 5773058|B440E6 | AN98: 45668 | AO98: 16004 | AP98: 7167
A99: B01 | B99: TYC EUROPE B.V. | C99: VEN0002107 | D99: =IFERROR(HYPERLINK(INDEX(вендори!F:F,MATCH(C99,вендори!A:A,0)),INDEX(вендори!F:F,MATCH(C99,вендори!A:A,0))),"") -> бланка | E99: 5773058 | F99: A944E5 | G99: TYC 18-3593-05-2 | H99: MRSU5298738 | I99: 5773058 | J99: 45961 | K99: 18-3593-05-2 | L99: 18-3593-05-2__18-3593-05-2 | M99: 2.95 | N99: 9 | O99: 18 | P99: 9 | Q99: Плюс | R99: 26.55 | S99: 51.927287 | T99: 45972 | U99: Подадена | X99: по сметка | AC99: ЧИ - Надето | AE99: 45961 | AF99: 8 | AG99: TYC | AH99: DEIVANOV | AI99: 5773058|A944E5 | AN99: 45668 | AO99: 16007 | AP99: 7167
A100: B01 | B100: Valeo Service Eastern Europe | C100: VEN0000668 | D100: =IFERROR(HYPERLINK(INDEX(вендори!F:F,MATCH(C100,вендори!A:A,0)),INDEX(вендори!F:F,MATCH(C100,вендори!A:A,0))),"") -> 0 | E100: 111076847 | F100: DA492E | G100: VAL851190 | H100: 26302498 | 26311525 | 80003245 | I100: 111076847 | J100: 45926 | K100: 851190 | L100: 851190 | M100: 68.34 | N100: 3 | O100: 2 | P100: -1 | Q100: Минус | R100: -68.34 | S100: -133.66142 | T100: 45972 | U100: отказана поради срок! | AE100: 45940 | AF100: 23 | AG100: VALEO | AH100: DEIVANOV | AI100: 111076847|DA492E | AN100: 30/10/2025 | AO100: 15887 | AP100: 6347
...

Sheet към доставчик
B1: INTER CARS BULGARIA CLAIM FORM - DELIVERY DISCREPANCIES
A2: B01 | B2: Supplier | C2: VEN0000779 | D2: деливъри задължително | E2: 2045269638 | F2: D006DB | G2: F 00V C17 504K | H2: Delivery | I2: Invoice No. | J2: Inv.date | K2: Ref. Number SUPPLIER | L2: F.00V.C17.504 | M2: 6.6 | N2: QTY invoiced | O2: QTY delivered | P2: Difference | Q2: Type of Difference | R2: 330 | S2: 645.4239 | T2: 26.6.2026 | AE2: 22.6.2026 | AG2: BOSCH | AH2: KMINKOV | AI2: 2045269638|D006DB | AQ2: delivery date
A3: B01 | B3: ContiTech Antriebssysteme GmbH | C3: VEN0000263 | D3: деливъри | E3: 3000223634 | F3: 321375 | G3: 4 PK 855 | I3: 3000223634 | J3: 46192 | K3: 4PK855 | L3: 4PK855 | M3: 3.48 | N3: 193 | O3: 213 | P3: 20 | Q3: =IF(P3>0,"surplus","short shipment") -> surplus | R3: 69.6 | S3: 136.12577 | T3: 46213 | U3: Подадена | AE3: 46205 | AG3: CONTITECH | AH3: VAPETROV | AI3: 3000223634|321375 | AQ3: 0400169017 | AR3: 004540
A4: B01 | B4: ContiTech Antriebssysteme GmbH | C4: VEN0000263 | D4: деливъри | E4: 3000223634 | F4: 262855 | G4: 4 PK 954 | I4: 3000223634 | J4: 46192 | K4: 4PK954 | L4: 4PK954 | M4: 4.51 | N4: 7 | O4: 14 | P4: 7 | Q4: =IF(P4>0,"surplus","short shipment") -> surplus | R4: 31.57 | S4: 61.745553 | T4: 46213 | U4: Подадена | AE4: 46205 | AG4: CONTITECH | AH4: VAPETROV | AI4: 3000223634|262855 | AQ4: 0400169017 | AR4: 000670
A5: B01 | B5: ContiTech Antriebssysteme GmbH | C5: VEN0000263 | D5: деливъри | E5: 3000223634 | F5: D67AA0 | G5: 5 PK 1150 K1 | I5: 3000223634 | J5: 46192 | K5: 5PK1150K1 | L5: 5PK1150K1 | M5: 22.27 | N5: 31 | O5: 25 | P5: -6 | Q5: =IF(P5>0,"surplus","short shipment") -> short shipment | R5: -133.62 | S5: -261.338 | T5: 46213 | U5: Подадена | AE5: 46205 | AG5: CONTITECH | AH5: VAPETROV | AI5: 3000223634|D67AA0 | AQ5: 0400120664 | AR5: 005730
A6: B01 | B6: ContiTech Antriebssysteme GmbH | C6: VEN0000263 | D6: деливъри | E6: 3000223634 | F6: B417A9 | G6: 6 PK 1670 | I6: 3000223634 | J6: 46192 | K6: 6PK1670 | L6: 6PK1670 | M6: 7.83 | N6: 25 | O6: 20 | P6: -5 | Q6: =IF(P6>0,"surplus","short shipment") -> short shipment | R6: -39.15 | S6: -76.570744 | T6: 46213 | U6: Подадена | AE6: 46205 | AG6: CONTITECH | AH6: VAPETROV | AI6: 3000223634|B417A9 | AQ6: 0400169017 | AR6: 003470
A7: B01 | B7: ContiTech Antriebssysteme GmbH | C7: VEN0000263 | D7: деливъри | E7: 3000223634 | F7: G1159K | G7: CT 1162 WP5 | I7: 3000223634 | J7: 46192 | K7: CT1162WP5 | L7: CT1162WP5 | M7: 63.1 | N7: 21 | O7: 20 | P7: -1 | Q7: =IF(P7>0,"surplus","short shipment") -> short shipment | R7: -63.1 | S7: -123.41287 | T7: 46213 | U7: Подадена | AE7: 46205 | AG7: CONTITECH | AH7: VAPETROV | AI7: 3000223634|G1159K | AQ7: 0400169017 | AR7: 005290
Q8: =IF(P8>0,"surplus","short shipment") -> short shipment
Q9: =IF(P9>0,"surplus","short shipment") -> short shipment
Q10: =IF(P10>0,"surplus","short shipment") -> short shipment
Q11: =IF(P11>0,"surplus","short shipment") -> short shipment
Q12: =IF(P12>0,"surplus","short shipment") -> short shipment
Q13: =IF(P13>0,"surplus","short shipment") -> short shipment
Q14: =IF(P14>0,"surplus","short shipment") -> short shipment
Q15: =IF(P15>0,"surplus","short shipment") -> short shipment
Q16: =IF(P16>0,"surplus","short shipment") -> short shipment
Q17: =IF(P17>0,"surplus","short shipment") -> short shipment
Q18: =IF(P18>0,"surplus","short shipment") -> short shipment
Q19: =IF(P19>0,"surplus","short shipment") -> short shipment
... Q168: =IF(P168>0,"surplus","short shipment") -> short shipment

Sheet вендори
A1: No. | B1: Name | C1: Currency Code | D1: Курс | E1: забележки, срокове, друго | F1: линк към сайт или спец.бланка
A2: VEN0000001 | B2: SC INTER CARS ROMANIA SRL | C2: EUR | D2: 1.95583
A3: VEN0000002 | B3: ОМВ БЪЛГАРИЯ ООД | C3: EUR | D3: 1.95583 | E3: от 01.01.26 вече е ЕВРО
A4: VEN0000003 | B4: INTER CARS SA | C4: EUR | D4: 1.95583
A5: VEN0000004 | B5: INTER CARS SA | C5: EUR | D5: 1.95583
A6: VEN0000005 | B6: ПРАКТИКЕР ЕООД | C6: EUR | D6: 1.95583 | E6: от 01.01.26 вече е ЕВРО
A7: VEN0000006 | B7: АГУРА ЕНД КО ЕООД | C7: EUR | D7: 1.95583 | E7: от 01.01.26 вече е ЕВРО
A8: VEN0000007 | B8: ШЕЛ БЪЛГАРИЯ ЕАД | C8: EUR | D8: 1.95583 | E8: от 01.01.26 вече е ЕВРО
A9: VEN0000008 | B9: МИДИЯ ИНВЕСТМЪНТ ЕООД | C9: EUR | D9: 1.95583 | E9: от 01.01.26 вече е ЕВРО
A10: VEN0000009 | B10: ЦЕНТЪР ЗА ПРЕВОДИ РЕЗОН ЕООД | C10: EUR | D10: 1.95583 | E10: от 01.01.26 вече е ЕВРО
A11: VEN0000010 | B11: НОТАРИУС МАРГАРИТА ИВАНЧЕВА | C11: EUR | D11: 1.95583 | E11: от 01.01.26 вече е ЕВРО
A12: VEN0000011 | B12: А1 БЪЛГАРИЯ ЕАД | C12: EUR | D12: 1.95583 | E12: от 01.01.26 вече е ЕВРО
A13: VEN0000012 | B13: ФУРНАРИ-ФФ ЕООД | C13: EUR | D13: 1.95583 | E13: от 01.01.26 вече е ЕВРО
A14: VEN0000013 | B14: КОНСУЛТИМ РИКРУИТМЪНТ ЕНД СЕЛЕ | C14: EUR | D14: 1.95583 | E14: от 01.01.26 вече е ЕВРО
A15: VEN0000014 | B15: БИСТРА И ГАЛИНА 2007 ЕООД | C15: EUR | D15: 1.95583 | E15: от 01.01.26 вече е ЕВРО
A16: VEN0000015 | B16: НОТАРИУС АЛЕКСАНДЪР ЧАКЪРОВ | C16: EUR | D16: 1.95583 | E16: от 01.01.26 вече е ЕВРО
A17: VEN0000016 | B17: ПЕТРОЛ АД | C17: EUR | D17: 1.95583 | E17: от 01.01.26 вече е ЕВРО
... A24: VEN0000023 | B24: БУЛГЕД ООД | C24: EUR | D24: 1.95583 | E24: от 01.01.26 вече е ЕВРО
A25: VEN0000024 | B25: АКОР - ПАНОНИЯ ХОТЕЛС ЗРТ | C25: HUF | D25: Check
A26: VEN0000025 | B26: О.С.Т. ГРАМАДА | C26: PLN | D26: 0.48
A27: VEN0000026 | B27: СЕРВИЗ ПЛЮС ООД | C27: EUR | D27: 1.95583 | E27: от 01.01.26 вече е ЕВРО
A28: VEN0000027 | B28: ТОДЕК ООД | C28: EUR | D28: 1.95583 | E28: от 01.01.26 вече е ЕВРО
A29: VEN0000028 | B29: ДАТЕКС ООД | C29: EUR | D29: 1.95583 | E29: от 01.01.26 вече е ЕВРО
A30: VEN0000029 | B30: МИРЕЛА ЕООД | C30: EUR | D30: 1.95583 | E30: от 01.01.26 вече е ЕВРО
A31: VEN0000030 | B31: БАРОМЕТЪР 31 ООД | C31: EUR | D31: 1.95583 | E31: от 01.01.26 вече е ЕВРО
A32: VEN0000031 | B32: МЕНИДЖМЪНТ ЕНД МАРКЕТИНГ ЕООД | C32: EUR | D32: 1.95583 | E32: от 01.01.26 вече е ЕВРО
A33: VEN0000032 | B33: СИСТЕМИ ЗА СИГУРНОСТ ЕООД | C33: EUR | D33: 1.95583 | E33: от 01.01.26 вече е ЕВРО
A34: VEN0000033 | B34: ПРОСЕТ ООД | C34: EUR | D34: 1.95583 | E34: от 01.01.26 вече е ЕВРО
A35: VEN0000034 | B35: ТЕД-ЕМ ООД | C35: EUR | D35: 1.95583 | E35: от 01.01.26 вече е ЕВРО
A36: VEN0000035 | B36: ХИТ ХИПЕРМАРКЕТ ЕООД | C36: EUR | D36: 1.95583 | E36: от 01.01.26 вече е ЕВРО
A37: VEN0000036 | B37: ИН ТАЙМ ООД | C37: EUR | D37: 1.95583 | E37: от 01.01.26 вече е ЕВРО
A38: VEN0000037 | B38: АДВ.ДРУЖ-ВО ДЕЛЧЕВ И ПАРТНЬОРИ | C38: EUR | D38: 1.95583 | E38: от 01.01.26 вече е ЕВРО
... A96: VEN0000095 | B96: ИЛИКОНИ ООД | C96: EUR | D96: 1.95583 | E96: от 01.01.26 вече е ЕВРО
A97: VEN0000096 | B97: PRACTICOM SRL | C97: EUR | D97: 1.95583
A98: VEN0000097 | B98: ЕЛИНА 97 ЕООД | C98: EUR | D98: 1.95583 | E98: от 01.01.26 вече е ЕВРО
A99: VEN0000098 | B99: ЕКОНТ ЕКСПРЕС ООД | C99: EUR | D99: 1.95583 | E99: от 01.01.26 вече е ЕВРО
A100: VEN0000099 | B100: БУЛТЕКС - 1 ООД | C100: EUR | D100: 1.95583 | E100: от 01.01.26 вече е ЕВРО
A101: VEN0000100 | B101: Ключарят ООД | C101: EUR | D101: 1.95583 | E101: от 01.01.26 вече е ЕВРО
A102: VEN0000101 | B102: ЕВРОМАРКЕТ КАРИ АД | C102: EUR | D102: 1.95583 | E102: от 01.01.26 вече е ЕВРО
A103: VEN0000102 | B103: ЛИФТ ООД | C103: EUR | D103: 1.95583 | E103: от 01.01.26 вече е ЕВРО
A104: VEN0000103 | B104: ЩАЙНБЕРГЕР ООД | C104: EUR | D104: 1.95583 | E104: от 01.01.26 вече е ЕВРО
A105: VEN0000104 | B105: БРОКЕР 2001 ЕООД | C105: EUR | D105: 1.95583 | E105: от 01.01.26 вече е ЕВРО
A106: VEN0000105 | B106: S.C. SPIDER CONNECTIONS SRL | C106: EUR | D106: 1.95583 | E106: от 01.01.26 вече е ЕВРО
A107: VEN0000106 | B107: БИРЕНА БОРСА РУСЕ ООД | C107: EUR | D107: 1.95583 | E107: от 01.01.26 вече е ЕВРО
A108: VEN0000107 | B108: ТБС ТРАДИКС ООД | C108: EUR | D108: 1.95583 | E108: от 01.01.26 вече е ЕВРО
A109: VEN0000108 | B109: ВИЛИ - АЛ СТРОЙ ЕООД | C109: EUR | D109: 1.95583 | E109: от 01.01.26 вече е ЕВРО
A110: VEN0000109 | B110: МУЛТИРАМА БЪЛГАРИЯ ООД | C110: EUR | D110: 1.95583 | E110: от 01.01.26 вече е ЕВРО
A111: VEN0000110 | B111: IKEA ROMANIA S.R.L. | C111: RON | D111: Check
A112: VEN0000111 | B112: ДИ ЕМ - 03 ЕООД | C112: EUR | D112: 1.95583 | E112: от 01.01.26 вече е ЕВРО
A113: VEN0000112 | B113: А И З 2010 ЕООД | C113: EUR | D113: 1.95583 | E113: от 01.01.26 вече е ЕВРО
A114: VEN0000113 | B114: КОМЕЛ СОФТ МУЛТИМЕДИЯ ЕООД | C114: EUR | D114: 1.95583 | E114: от 01.01.26 вече е ЕВРО
A115: VEN0000114 | B115: ДРИЙМВИЛ ООД | C115: EUR | D115: 1.95583 | E115: от 01.01.26 вече е ЕВРО
A116: VEN0000115 | B116: НОТАРИУС ЛИЛИ ЛАКОВА | C116: EUR | D116: 1.95583 | E116: от 01.01.26 вече е ЕВРО
A117: VEN0000116 | B117: СОЛВИ ООД | C117: EUR | D117: 1.95583 | E117: от 01.01.26 вече е ЕВРО
A118: VEN0000117 | B118: ДЕДРАКС АД | C118: EUR | D118: 1.95583 | E118: от 01.01.26 вече е ЕВРО
A119: VEN0000118 | B119: СОНЕВ И СИНОВЕ СД | C119: EUR | D119: 1.95583 | E119: от 01.01.26 вече е ЕВРО
A120: VEN0000119 | B120: КИПА ООД | C120: EUR | D120: 1.95583 | E120: от 01.01.26 вече е ЕВРО
A121: VEN0000120 | B121: ИНТЕРЛИЙЗ АУТО ЕАД | C121: EUR | D121: 1.95583 | E121: от 01.01.26 вече е ЕВРО
A122: VEN0000121 | B122: СОТ ЕООД | C122: EUR | D122: 1.95583 | E122: от 01.01.26 вече е ЕВРО
A123: VEN0000123 | B123: КОРЕКТ ТУР ООД | C123: EUR | D123: 1.95583 | E123: от 01.01.26 вече е ЕВРО
... A145: VEN0000145 | B145: НОРД ЕЛРЕЦИКЛИНГ АД | C145: EUR | D145: 1.95583 | E145: от 01.01.26 вече е ЕВРО
A146: VEN0000146 | B146: INTER CARS CZECH REPUBLIK SRO | C146: EUR | D146: 1.95583
A147: VEN0000147 | B147: СВЕТЛАНА 92 - Т Марг.Тодорова | C147: EUR | D147: 1.95583 | E147: от 01.01.26 вече е ЕВРО
A148: VEN0000148 | B148: ВАЛДИ ЛКВ ООД | C148: EUR | D148: 1.95583 | E148: от 01.01.26 вече е ЕВРО
A149: VEN0000149 | B149: БУЛГАРПРЕС ООД | C149: EUR | D149: 1.95583 | E149: от 01.01.26 вече е ЕВРО
A150: VEN0000150 | B150: КЛИМА ТЕХНОЛОДЖИ ЕООД | C150: EUR | D150: 1.95583 | E150: от 01.01.26 вече е ЕВРО
A151: VEN0000151 | B151: ПРИМЕКС ЕООД | C151: EUR | D151: 1.95583 | E151: от 01.01.26 вече е ЕВРО
A152: VEN0000152 | B152: ПРИНТ-МЕДЖИК ЕУ ЕООД | C152: EUR | D152: 1.95583 | E152: от 01.01.26 вече е ЕВРО
A153: VEN0000153 | B153: МАКСИ - 1 АД | C153: EUR | D153: 1.95583 | E153: от 01.01.26 вече е ЕВРО
A154: VEN0000154 | B154: ДИВЕСТА ООД | C154: EUR | D154: 1.95583 | E154: от 01.01.26 вече е ЕВРО
A155: VEN0000155 | B155: MY AGENCY S.R.O. | C155: EUR | D155: 1.95583
A156: VEN0000156 | B156: СДРУЖЕНИЕ РУСЕ КАР МОТОР СПОРТ | C156: EUR | D156: 1.95583 | E156: от 01.01.26 вече е ЕВРО
A157: VEN0000157 | B157: СТЕП-СОФТ ООД | C157: EUR | D157: 1.95583 | E157: от 01.01.26 вече е ЕВРО
A158: VEN0000158 | B158: Д И Д ЕКСПРЕС ЕООД | C158: EUR | D158: 1.95583 | E158: от 01.01.26 вече е ЕВРО
A159: VEN0000159 | B159: ТРАНСКОМ-АВТОГАРА ЕООД | C159: EUR | D159: 1.95583 | E159: от 01.01.26 вече е ЕВРО
A160: VEN0000160 | B160: ФАВОРИТ 98 ЕООД | C160: EUR | D160: 1.95583 | E160: от 01.01.26 вече е ЕВРО
A161: VEN0000161 | B161: УЛТРАПАК ЕООД | C161: EUR | D161: 1.95583 | E161: от 01.01.26 вече е ЕВРО
A162: VEN0000162 | B162: ЕКСПРЕС ГАРАНЦИОН ООД | C162: EUR | D162: 1.95583 | E162: от 01.01.26 вече е ЕВРО
A163: VEN0000163 | B163: АНАКОНДА | C163: EUR | D163: 1.95583 | E163: от 01.01.26 вече е ЕВРО
A164: VEN0000164 | B164: ДОМЪТ ООД | C164: EUR | D164: 1.95583 | E164: от 01.01.26 вече е ЕВРО
A165: VEN0000165 | B165: Нотариус Жана Тикова | C165: EUR | D165: 1.95583 | E165: от 01.01.26 вече е ЕВРО
A166: VEN0000166 | B166: АЙ ДЖИ ДИ ТУР ООД | C166: EUR | D166: 1.95583 | E166: от 01.01.26 вече е ЕВРО
A167: VEN0000167 | B167: S.C. SPIDER CONNECTIONS SRL | C167: EUR | D167: 1.95583
A168: VEN0000168 | B168: ВИЗА СИТИ ЕООД | C168: EUR | D168: 1.95583 | E168: от 01.01.26 вече е ЕВРО
A169: VEN0000169 | B169: ТЕХНОТРЕЙД АРТОН СИСТЕМС ЕООД | C169: EUR | D169: 1.95583 | E169: от 01.01.26 вече е ЕВРО
A170: VEN0000170 | B170: ХЕМУС 2005 ЕООД | C170: EUR | D170: 1.95583 | E170: от 01.01.26 вече е ЕВРО
A171: VEN0000171 | B171: ФИНЕС ООД | C171: EUR | D171: 1.95583 | E171: от 01.01.26 вече е ЕВРО
A172: VEN0000172 | B172: СИГНАЛ - ДЕЛЯН КОЛЧЕВ ЕТ | C172: EUR | D172: 1.95583 | E172: от 01.01.26 вече е ЕВРО
A173: VEN0000173 | B173: ХАМА ЕООД | C173: EUR | D173: 1.95583 | E173: от 01.01.26 вече е ЕВРО
A174: VEN0000174 | B174: ЕЛИТ 94 -М.ПАВЛОВ ООД | C174: EUR | D174: 1.95583 | E174: от 01.01.26 вече е ЕВРО
A175: VEN0000175 | B175: АЙ БИ ЕС БЪЛГАРИЯ ЕООД | C175: EUR | D175: 1.95583 | E175: от 01.01.26 вече е ЕВРО
A176: VEN0000176 | B176: Hotel KORONA Sp. z.o.o. | C176: PLN | D176: 0.48
A177: VEN0000177 | B177: ГВ ДИЗАЙН ООД | C177: EUR | D177: 1.95583 | E177: от 01.01.26 вече е ЕВРО
A178: VEN0000178 | B178: Мебели Лудвик Бълг.ЕООД COMO | C178: EUR | D178: 1.95583 | E178: от 01.01.26 вече е ЕВРО
A179: VEN0000179 | B179: МАРВИПАК ЕООД | C179: EUR | D179: 1.95583 | E179: от 01.01.26 вече е ЕВРО
A180: VEN0000180 | B180: ЖОРМАНИ ООД | C180: EUR | D180: 1.95583 | E180: от 01.01.26 вече е ЕВРО
A181: VEN0000181 | B181: ТИП ТОП КУРИЕР АД | C181: EUR | D181: 1.95583 | E181: от 01.01.26 вече е ЕВРО
A182: VEN0000182 | B182: ВАРНА-ИНТЕР-ПАРТНЪР ООД | C182: EUR | D182: 1.95583 | E182: от 01.01.26 вече е ЕВРО
A183: VEN0000183 | B183: ЕКОНТ ТРАНС АД | C183: EUR | D183: 1.95583 | E183: от 01.01.26 вече е ЕВРО
A184: VEN0000184 | B184: ЕВРОПЪТ 2000 АД | C184: EUR | D184: 1.95583 | E184: от 01.01.26 вече е ЕВРО
...

Sheet срокове
A1: Vendor No. | B1: Срок на подаване към доставчика - инфо от РМ | C1: Пълно име на вендора | D1: Забележка
A2: VEN0001181 | B2: няма ограничение, но възможно най-скоро | C2: ADRIAUTO
A3: VEN0001262 | B3: няма ограничение, но възможно най-скоро | C3: ASMET SP. Z O.O.
A4: VEN0001327 | B4: няма ограничение, но възможно най-скоро | C4: ASSO MARMITTE SRL
A5: VEN0001382 | B5: няма ограничение, но възможно най-скоро | C5: AUTO JUNTAS S.A.UNIPERSONAL
A6: VEN0000934 | B6: няма ограничение, но възможно най-скоро | C6: AUTOPART S.A.
A7: VEN0001258 | B7: няма ограничение | C7: BORGWARNER AFTERMARKET EUROPE GMBH
A8: VEN0001231 | B8: няма ограничение, но възможно най-скоро | C8: BOSAL AFTERMARKET EUROPE SPOL. S R.O.
A9: VEN0001264 | B9: няма ограничение, но възможно най-скоро | C9: CAFFARO SPÓŁKA Z OGR. ODPOWI. SP KOMANDYTOWA
A10: VEN0001275 | B10: 14 days, 14 дни | C10: CEI COSTRUZIONE EMILIANA INGRANAGGI SPA
A11: VEN0000766 | B11: няма ограничение, но възможно най-скоро | C11: Clarios Germany GmbH & Co. KGaA (CZ)
A12: VEN0001137 | B12: няма ограничение, но възможно най-скоро | C12: CONTINENTAL AFTERMARKET GMBH
A13: VEN0001616 | B13: няма ограничение, но възможно най-скоро | C13: CONTINENTAL TRADING GMBH
... A24: VEN0001317 | B24: 30 days since delivery date/ within 7 days after delivery date | C24: FEDERAL MOGUL GLOBAL AFTERMARKET EMEA BVBA HUNGARI
A25: VEN0001136 | B25: ASAP, възможно най-скоро | C25: FERDINAND BILSTEIN GMBH + CO. KG | D25: имаме 0,2% за рекламациии на база покупки - дефектни артикули се подават към отдел Рекламации
A26: VEN0001249 | B26: няма ограничение, но възможно най-скоро | C26: FRANCISCO ALBERO S.A.U.
A27: VEN0001243 | B27: няма ограничение, но възможно най-скоро | C27: FRECCIA INTERNATIONAL S.R.L. | D27: вече имат ексел -бланка и издават документите в началото на следващия месец
A28: VEN0001443 | B28: any discrepancies from deliveries should be reported within a maximum of 4 weeks after delivery | C28: GATES INDUSTRIAL EUROPE SARL
A29: VEN0001511 | B29: not to late (?) , не твърде късно | C29: GKN DRIVELINE SERVICE GMBH
A30: VEN0001253 | B30: two weeks after delivery on your warehouse. Till this time, we are able to check the status on camera . | C30: GROUP STEINHOF SP.Z.O.O | D30: We have to receive this kind of report till 3 weeks from delivery date .
A31: VEN0001281 | B31: няма ограничение | C31: HELLA POLSKA SP. Z O.O.
A32: VEN0001260 | B32: няма ограничение, но възможно най-скоро | C32: HERTH+BUSS FAHRZEUGTEILE GMBH & CO. KG
A33: VEN0001330 | B33: няма ограничение, но възможно най-скоро | C33: HIDRIA D.O.O.
A34: VEN0001555 | B34: няма ограничение, но възможно най-скоро | C34: HITACHI AUTOMOTIVE SYSTEMS ESPELKAMP GMBH
A35: VEN0001473 | B35: 7 days from receipt, 7 дни от доставката | C35: INDUSTRIAS DOLZ S.A.
A36: VEN0000925 | B36: няма ограничение, но възможно най-скоро | C36: INDUSTRIE SALERI ITALO S.P.A.
A37: VEN0001282 | B37: няма ограничение, но възможно най-скоро | C37: IPD INDUSTRIAL PARTS DISTRIBUTION GMBH
A38: VEN0000946 | B38: няма ограничение, но възможно най-скоро | C38: JENOX AKUMULATORY
A39: VEN0001241 | B39: 7 days from receiving , 7 дни от доставката | C39: KYB EUROPE GMBH
A40: VEN0001287 | B40: няма ограничение, но възможно най-скоро | C40: LAUBER SP. Z O.O.
A41: VEN0001285 | B41: ASAP, възможно най-скоро | C41: LE.MA SRL
A42: VEN0001242 | B42: not specified , не е подадена информация | C42: LESJOFORS SPRINGS GMBH
A43: VEN0001286 | B43: not specified , не е подадена информация | C43: LINEX SP. Z O.O.
A44: VEN0001908 | B44: not specified , не е подадена информация | C44: LORO | D44: sales@loro.com.pl
A45: VEN0001234 | B45: няма ограничение, но възможно най-скоро | C45: LPR SRL
A46: VEN0001316 | B46: Има ограничение - 7 дни от датата на получаване на стоката | C46: LUMILEDS POLAND S.A.
A47: VEN0000375 | B47: Има ограничение - 7 дни от датата на получаване на стоката | C47: Magneti Marelli Aftermarket
A48: VEN0001259 | B48: Има ограничение - 14 дни от датата на получаване на стоката | C48: MAHLE AFTERMARKET GMBH
A49: VEN0000533 | B49: Има ограничение - 14 дни от датата на получаване на стоката | C49: MANN HUMMEL GERMANY | D49: срокът за подаване е от 20.09.2024 - within 2 weeks after receiving the goods
A50: VEN0000282 | B50: няма ограничение, но възможно най-скоро | C50: MANN+HUMMEL FILTR. Sp. z o.o.
A51: VEN0001192 | B51: 7 days from receipt, 7 дни от доставката | C51: MEYLE AG
A52: VEN0001288 | B52: няма ограничение, но възможно най-скоро | C52: MOBILETRON UK LTD.
A53: VEN0001263 | B53: няма ограничение, но възможно най-скоро | C53: MOTO REMO BURZYŃSCY SP.J.
A54: VEN0001314 | B54: няма ограничение, но възможно най-скоро | C54: MS MOTORSERVICE INTERNATIONAL GMBH
A55: VEN0001353 | B55: няма ограничение, но възможно най-скоро | C55: NGK Spark Plug Europe GmbH
A56: VEN0001361 | B56: няма ограничение, но възможно най-скоро | C56: NISSENS AUTOMOTIVE A/S
A57: VEN0001265 | B57: няма ограничение, но възможно най-скоро | C57: NL MOTO S.R.O
A58: VEN0000736 | B58: two weeks of the receipt date | C58: NRF POLAND Sp.z o.o. | D58: от 06.11.25 мейл
A59: VEN0001261 | B59: няма ограничение, но възможно най-скоро | C59: NTN-SNR ROULEMENTS
A60: VEN0001233 | B60: няма ограничение, но възможно най-скоро | C60: OJD QUICK BRAKE APS
A61: VEN0001078 | B61: Има ограничение - 4 дни от датата на получаване на стоката | C61: OSRAM D.O.O
A62: VEN0001248 | B62: няма ограничение, но възможно най-скоро | C62: REINZ-DICHTUNGS-GMBH
A63: VEN0000779 | B63: 3 дни от датата на доставка | C63: ROBERT BOSCH S.R.L.
A64: VEN0002011 | B64: 1 месец: up to one month after receiving the shipment | C64: ROULUNDS BRAKING APS._SBP
A65: VEN0001290 | B65: 7 days , 7 дни | C65: S.A.S.I.C. - S.A.SANTUCCI SICFA REUNIS
A66: VEN0000463 | B66: 7 working days , за количества и видими разлики - незабавно след получаване на стоката | C66: Schaeffler Automot.Aftermarket
A67: VEN0001232 | B67: няма ограничение, но възможно най-скоро | C67: SEGURIDAD INDUSTRIAL, S.A.
A68: VEN0001590 | B68: няма ограничение, но възможно най-скоро | C68: SKF EUROTRADE AB
A69: VEN0001280 | B69: няма ограничение, но възможно най-скоро | C69: SWAG AUTOTEILE GMBH
A70: VEN0001289 | B70: 30 days, 30 дни | C70: TEDGUM TADEUSZ WOJCIECHOWSKI
A71: VEN0001235 | B71: 3 months after invoice date , 3 месеца от датата на фактурата | C71: TENNECO AUTOMOTIVE EUROPE BVBA | D71: за този доставчик не се подават рекламации за дефектен артикул - има годишен бонус 0,5%, който да покрива тези случаи
A72: VEN0001256 | B72: няма ограничение, но възможно най-скоро | C72: TOMEX A.J.C. TOMCZYK SP.J.
A73: VEN0000310 | B73: няма ограничение, но възможно най-скоро | C73: TRW KFZ Ausrustung GmbH
A74: VEN0001254 | B74: Има ограничение - 3 дни от датата на получаване на стоката | C74: TYC EUROPE B.V.
A75: VEN0000668 | B75: 2 weeks, 10 working days, 2 седмици, 10 раб.дни от датата на доставката по CMR | C75: Valeo Service Eastern Europe
A76: VEN0001276 | B76: 30 days, 30 дни | C76: VANSTAR PRZEDSIĘBIORSTWO WIELOBRANŻOWE PAWEŁ SZOST
A77: VEN0001257 | B77: Има ограничение - 7 дни от датата на получаване на стоката | C77: VERNET SAS
A78: VEN0001269 | B78: няма ограничение, но възможно най-скоро | C78: VIEROL AG | D78: в мейл бяха посочили 3 дни от датата на доставката!
A79: VEN0001426 | B79: Unknown, не е подадена информация, възможно най-скоро | C79: WABCO Austria GesmbH
A80: VEN0001053 | B80: Ново от 18.2.2025: 14 days after goods arrival at his place about the missing/overdelivered Items | C80: ZF FRIEDRICHSHAFEN AG | D80: In future, please be so kind and send the claims like, warranties, defective parts, incorrect packing etc. to me salessupport.neuwied@zf.com. - за TRW е Sandra, а за SACHS -> Schweinfurt ->frank.wetzel@zf.com . Claims regarding delivery differences & Transport damages should be communicated to COM dept. ordermngmt.iamneuwied@zf.com. Claims regarding delivery differences & Transport damages should be communicated to COM dept. ordermngmt.iamneuwied@zf.com. After internal check, you are right, only warranty parts (after installation/mounted parts) are covered by the flat rate as agreed in the agreement 2021.

Sheet за счетоводството
F1: Вътр.№ | G1: Активен № | P1: к-во | V1: Документ № | W1: Дата на док. | X1: клетка | Y1: забележка
A2: B01 | B2: HEPU-Autoteile GmbH | C2: VEN0003385 | D2: 0 | E2: 2026403157 | F2: H0FPPW | G2: HEP21-0671 | H2: 62550 | 2026-403154 | I2: 2026-403157 | J2: 46161 | K2: 21-0671 | M2: 359.2 | N2: 1 | O2: 0 | P2: -1 | Q2: Минус | R2: -359.2 | S2: -702.53414 | T2: 46181 | U2: Получено КИ | V2: 2026-403605 | W2: 46183 | X2: =IF(P2<0,"B01-NOT-DELIV-DIRECT","прием") -> B01-NOT-DELIV-DIRECT | AE2: 46169 | AG2: HEPU | AH2: VAPETROV | AI2: 2026403157|H0FPPW | AN2: 46178 | AO2: 25812 | AP2: 13144
X3: =IF(P3<0,"B01-NOT-DELIV-DIRECT","прием") -> прием
X4: =IF(P4<0,"B01-NOT-DELIV-DIRECT","прием") -> прием
X5: =IF(P5<0,"B01-NOT-DELIV-DIRECT","прием") -> прием
X6: =IF(P6<0,"B01-NOT-DELIV-DIRECT","прием") -> прием
X7: =IF(P7<0,"B01-NOT-DELIV-DIRECT","прием") -> прием
X8: =IF(P8<0,"B01-NOT-DELIV-DIRECT","прием") -> прием
X9: =IF(P9<0,"B01-NOT-DELIV-DIRECT","прием") -> прием
X10: =IF(P10<0,"B01-NOT-DELIV-DIRECT","прием") -> прием
X11: =IF(P11<0,"B01-NOT-DELIV-DIRECT","прием") -> прием
X12: =IF(P12<0,"B01-NOT-DELIV-DIRECT","прием") -> прием
X13: =IF(P13<0,"B01-NOT-DELIV-DIRECT","прием") -> прием
X14: =IF(P14<0,"B01-NOT-DELIV-DIRECT","прием") -> прием
... X25: =IF(P25<0,"B01-NOT-DELIV-DIRECT","прием") -> прием

Sheet статуси и легенда цветове
A1: Подадена | H1: Легенда цветове на шрифта:
A2: Разлика под 50лв. | H2: 123456 | I2: направена е инв. От Митко - януари 2025, положителна - плюсове
A3: Получено КИ | H3: 123456 | I3: направена е инв. От Митко - януари 2025, отрицателна - минуси
A4: Получено ДИ/фактура | H4: 123456 | I4: подадени от Руми на месечна база за корекция към склада
A5: КИ и ДИ в един документ | H5: 123456 | I5: bold - намерени, които Руми още не проверила дали са подадени, или не (след обработка блод-а се маха)
A6: Изтекъл срок за подаване | H6: 123456 | I6: всички останали, стандартни
A7: За доуточняване | H7: 123456 | I7: специални, нещо за проверка, да се обърне внимание, да се провери, да се внимава за друга кореспондеция или нещо подобно
A8: одобрена от доставчика, чака документ | I8: ако са маркирани така, значи са счупени или повредени, но НЕ СА липси
A9: Отказани | I9: за проверка от Тони, склада (или бройките не са ок, или номерата, или се дублират, или има грешки в кроса - Руми)
A10: Анулирана
A11: За бракуване
A12: За връщане или върнато
A13: издадена ф-ра към ДД
A14: изпратени от дост.впосл.
A15: коригира се с ИНВЕНТАРИЗАЦИЯ
A16: МАСЛА - обработва се от РМ
A17: отказана, но впосл. НАМЕРЕНА в склада!
A18: отказана поради срок!
A19: Гуми или OE - обработва се от РМ
A20: Сервизно - обработва се от СО

Sheet В01 програма
A1: № | B1: Доставка № | C1: Доставчик | D1: Доставчик № | E1: Номер прием | F1: Вътрешен № | G1: Активен № | H1: Доставка № | I1: Quantity | J1: Плюс-Минус | K1: Тип | L1: Прием генериран на | M1: Зона | N1: Коментар | O1: Коментар Админ
A2: 27439 | B2: 14399 | C2: HSN TUNNEL-ROMIX | D2: VEN0001367 | E2: 000423/BLX/2026/UE | F2: BFD5D8 | G2: ROM C60332 | H2: 000423/BLX/2026/UE | I2: 60 | J2: Плюс | K2: Директни | L2: 46206 | M2: Ниво 3
A3: 27500 | B3: 13627 | C3: MANN HUMMEL GERMANY | D3: VEN0000533 | E3: 101275603 | F3: D06C2C | G3: C 27 1250/1 | H3: 980798 | I3: -42 | J3: Минус | K3: Директни | L3: 46184 | M3: Ниво 3
A4: 27502 | B4: 13627 | C4: MANN HUMMEL GERMANY | D4: VEN0000533 | E4: 101275603 | F4: H068NX | G4: TB 1374/13 X | H4: 980798 | I4: -10 | J4: Минус | K4: Директни | L4: 46184 | M4: Ниво 3
A5: 27501 | B5: 13627 | C5: MANN HUMMEL GERMANY | D5: VEN0000533 | E5: 101275603 | F5: D06F44 | G5: WP 12 300 | H5: 980798 | I5: -10 | J5: Минус | K5: Директни | L5: 46184 | M5: Ниво 3
A6: 27304 | B6: 14045 | C6: Valeo Service Eastern Europe | D6: VEN0000668 | E6: 111083178 | F6: G0QNP7 | G6: VAL200284 | H6: 26702302 | 26702303 | 26714082 | 26714087 | 26702159 | I6: -1 | J6: Минус | K6: Директни | L6: 46197 | M6: Ниво 0
A7: 27305 | B7: 14045 | C7: Valeo Service Eastern Europe | D7: VEN0000668 | E7: 111083178 | F7: G0UYL7 | G7: VAL440999 | H7: 26702302 | 26702303 | 26714082 | 26714087 | 26702159 | I7: -1 | J7: Минус | K7: Директни | L7: 46197 | M7: Ниво 0
A8: 27303 | B8: 14045 | C8: Valeo Service Eastern Europe | D8: VEN0000668 | E8: 111083178 | F8: F8E7A5 | G8: VAL837437 | H8: 26702302 | 26702303 | 26714082 | 26714087 | 26702159 | I8: -1 | J8: Минус | K8: Директни | L8: 46197 | M8: Ниво 0
A9: 27390 | B9: 14367 | C9: FERDINAND BILSTEIN GMBH | D9: VEN0001136 | E9: 12562980 | F9: 368512 | G9: FE01293 | H9: 709999390 | 709999391 | 709999384 | I9: 6 | J9: Плюс | K9: Директни | L9: 46206 | M9: Ниво 1
A10: 27362 | B10: 14385 | C10: MS MOTORSERVICE | D10: VEN0001314 | E10: 2430441852 | F10: AE9AAE | G10: 20190390600 | H10: 80821757 | 80821546 | I10: -1 | J10: Минус | K10: Директни | L10: 46206 | M10: Ниво 2
A11: 27363 | B11: 14385 | C11: MS MOTORSERVICE | D11: VEN0001314 | E11: 2430441864 | F11: DE38D3 | G11: 7.07381.00.0 | H11: 80821757 | 80821546 | I11: -1 | J11: Минус | K11: Директни | L11: 46206 | M11: Ниво 2
A12: 27293 | B12: 14353 | C12: MS MOTORSERVICE | D12: VEN0001314 | E12: 2430441874 | F12: C5D366 | G12: 20190220660 | H12: 80821756 | I12: 1 | J12: Плюс | K12: Директни | L12: 46205 | M12: Ниво 2
A13: 27291 | B13: 14353 | C13: MS MOTORSERVICE | D13: VEN0001314 | E13: 2430441874 | F13: C00D83 | G13: 7.00272.03.0 | H13: 80821756 | I13: 2 | J13: Плюс | K13: Директни | L13: 46205 | M13: Ниво 2
A14: 27292 | B14: 14353 | C14: MS MOTORSERVICE | D14: VEN0001314 | E14: 2430441874 | F14: H0FI7U | G14: 7.09460.15.0 | H14: 80821756 | I14: 1 | J14: Плюс | K14: Директни | L14: 46205 | M14: Ниво 2
A15: 27271 | B15: 14273 | C15: HANS PRIES DIRECT | D15: VEN0003766 | E15: 26-206216 | F15: G0KLIH | G15: HP117 457 | H15: 26-206216 | I15: -12 | J15: Минус | K15: Директни | L15: 46204 | M15: Ниво 2
A16: 27435 | B16: 14318 | C16: ContiTech Antriebssysteme GmbH | D16: VEN0000263 | E16: 3000223634 | F16: 321375 | G16: 4 PK 855 | H16: 60387227 | 60380482 | 60377473 | 60374288 | I16: 20 | J16: Плюс | K16: Директни | L16: 46205 | M16: Ниво 3
A17: 27433 | B17: 14318 | C17: ContiTech Antriebssysteme GmbH | D17: VEN0000263 | E17: 3000223634 | F17: 262855 | G17: 4 PK 954 | H17: 60387227 | 60380482 | 60377473 | 60374288 | I17: 7 | J17: Плюс | K17: Директни | L17: 46205 | M17: Ниво 3
A18: 27430 | B18: 14318 | C18: ContiTech Antriebssysteme GmbH | D18: VEN0000263 | E18: 3000223634 | F18: D67AA0 | G18: 5 PK 1150 K1 | H18: 60387227 | 60380482 | 60377473 | 60374288 | I18: -6 | J18: Минус | K18: Директни | L18: 46205 | M18: Ниво 3
A19: 27428 | B19: 14318 | C19: ContiTech Antriebssysteme GmbH | D19: VEN0000263 | E19: 3000223634 | F19: B417A9 | G19: 6 PK 1670 | H19: 60387227 | 60380482 | 60377473 | 60374288 | I19: -5 | J19: Минус | K19: Директни | L19: 46205 | M19: Ниво 3
A20: 27432 | B20: 14318 | C20: ContiTech Antriebssysteme GmbH | D20: VEN0000263 | E20: 3000223634 | F20: G1159K | G20: CT 1162 WP5 | H20: 60387227 | 60380482 | 60377473 | 60374288 | I20: -1 | J20: Минус | K20: Директни | L20: 46205 | M20: Ниво 3
A21: 27301 | B21: 14090 | C21: FEDERAL MOGUL EMEA | D21: VEN0001842 | E21: 3000739942 | F21: G0OC6W | G21: BCV29264TK | H21: 35591161 | I21: -5 | J21: Минус | K21: Директни | L21: 46198 | M21: Ниво 0
A22: 27311 | B22: 14090 | C22: FEDERAL MOGUL EMEA | D22: VEN0001842 | E22: 3000739952 | F22: 223620 | G22: 08-245200-00 | H22: 35591161 | I22: -10 | J22: Минус | K22: Директни | L22: 46198 | M22: Ниво 2
A23: 27309 | B23: 14090 | C23: FEDERAL MOGUL EMEA | D23: VEN0001842 | E23: 3000739952 | F23: D4876E | G23: BCR214A | H23: 35591161 | I23: -4 | J23: Минус | K23: Директни | L23: 46198 | M23: Ниво 2
A24: 27313 | B24: 14090 | C24: FEDERAL MOGUL EMEA | D24: VEN0001842 | E24: 3000739953 | F24: DC26DF | G24: CH-LS-10133 | H24: 35591161 | I24: -8 | J24: Минус | K24: Директни | L24: 46198 | M24: Ниво 2
A25: 27302 | B25: 14090 | C25: FEDERAL MOGUL EMEA | D25: VEN0001842 | E25: 3000739954 | F25: 315186 | G25: FVR1102 | H25: 35591161 | I25: -9 | J25: Минус | K25: Директни | L25: 46198 | M25: Ниво 0
A26: 27448 | B26: 14334 | C26: MAHLE AFTERMARKET GMBH | D26: VEN0001259 | E26: 398761474 | F26: G08FBW | G26: CFF 471 000P | H26: 6373593 | 6373594 | 6380449 | I26: -2 | J26: Минус | K26: Директни | L26: 46205 | M26: Ниво 2
A27: 27482 | B27: 13703 | C27: Schaeffler Automot.Aftermarket | D27: VEN0000463 | E27: 423692516 | F27: F8248C | G27: 544 0088 20 | H27: 62422496 | 62422234 | 62422519 | I27: -5 | J27: Минус | K27: Директни | L27: 46188 | M27: Ниво 1
A28: 27483 | B28: 13703 | C28: Schaeffler Automot.Aftermarket | D28: VEN0000463 | E28: 423692516 | F28: D0B031 | G28: 712 0580 10 | H28: 62422496 | 62422234 | 62422519 | I28: -18 | J28: Минус | K28: Директни | L28: 46188 | M28: Ниво 1
A29: 27299 | B29: 14247 | C29: Schaeffler Automot.Aftermarket | D29: VEN0000463 | E29: 423697416 | F29: A9965D | G29: 624 3103 33 | H29: 62438991 | 62438996 | I29: 1 | J29: Плюс | K29: Директни | L29: 46203 | M29: Ниво 0
A30: 27473 | B30: 14509 | C30: FROGUM DIRECT DELIVERYES | D30: VEN0002039 | E30: 5/ 7/SU/2026 | F30: G0X14X | G30: FRG77409460 | H30: 5/ 7/SU/2026 | I30: -2 | J30: Минус | K30: Директни | L30: 46210 | M30: Б. П.
A31: 27472 | B31: 14509 | C31: FROGUM DIRECT DELIVERYES | D31: VEN0002039 | E31: 5/ 7/SU/2026 | F31: D75935 | G31: MMT A040 00992W2 | H31: 5/ 7/SU/2026 | I31: -2 | J31: Минус | K31: Директни | L31: 46210 | M31: Б. П.
A32: 27446 | B32: 14343 | C32: ZF / FRIEDRICHSHAFEN AG | D32: VEN0001053 | E32: 5013860425 | F32: D701DB | G32: LMI36532 | H32: 166207035 | 166207118 | 166207119 | 166207141 | 166207164 | 166207036 | I32: -2 | J32: Минус | K32: Директни | L32: 46205 | M32: Ниво 1
A33: 27492 | B33: 14450 | C33: TRW / ZF- CZECH | D33: VEN0003781 | E33: 5013870887 | F33: AF39A8 | G33: DF4274BS | H33: 166156113 | 166188636 | 166188641 | I33: 1 | J33: Плюс | K33: Директни | L33: 46209 | M33: Ниво 0
A34: 27489 | B34: 14450 | C34: TRW / ZF- CZECH | D34: VEN0003781 | E34: 5013870887 | F34: B38D11 | G34: GDB1736 | H34: 166156113 | 166188636 | 166188641 | I34: -3 | J34: Минус | K34: Директни | L34: 46209 | M34: Ниво 0
A35: 27491 | B35: 14450 | C35: TRW / ZF- CZECH | D35: VEN0003781 | E35: 5013870887 | F35: BE20D0 | G35: GDB1847 | H35: 166156113 | 166188636 | 166188641 | I35: 3 | J35: Плюс | K35: Директни | L35: 46209 | M35: Ниво 0
A36: 27490 | B36: 14450 | C36: TRW / ZF- CZECH | D36: VEN0003781 | E36: 5013870887 | F36: BB905C | G36: PHB562 | H36: 166156113 | 166188636 | 166188641 | I36: -8 | J36: Минус | K36: Директни | L36: 46209 | M36: Ниво 0
A37: 27505 | B37: 14327 | C37: GATES | D37: VEN0001443 | E37: 5200011582 | F37: H07R6N | G37: GATK04T360HOB | H37: 80095534 | 80101230 | I37: -1 | J37: Минус | K37: Директни | L37: 46205 | M37: Ниво 3
A38: 27508 | B38: 14327 | C38: GATES | D38: VEN0001443 | E38: 5200011582 | F38: H0GOUL | G38: GATK05T360HOB | H38: 80095534 | 80101230 | I38: 1 | J38: Плюс | K38: Директни | L38: 46205 | M38: Ниво 3
A39: 27506 | B39: 14327 | C39: GATES | D39: VEN0001443 | E39: 5200012016 | F39: E4D086 | G39: GATK015537XS | H39: 80095534 | 80101230 | I39: -5 | J39: Минус | K39: Директни | L39: 46205 | M39: Ниво 3
A40: 27317 | B40: 14441 | C40: ОСРАМ СЕЙЛС ЕООД | D40: VEN0002997 | E40: 925012043 | F40: E65886 | G40: NLX233 K10SZT | H40: 925012043 | I40: -495 | J40: Минус | K40: Директни | L40: 46209 | M40: Ниво 3
A41: 27318 | B41: 14441 | C41: ОСРАМ СЕЙЛС ЕООД | D41: VEN0002997 | E41: 925012043 | F41: H0KLJA | G41: OSR7506DWP-2BL | H41: 925012043 | I41: -20 | J41: Минус | K41: Директни | L41: 46209 | M41: Ниво 3
A42: 27316 | B42: 14441 | C42: ОСРАМ СЕЙЛС ЕООД | D42: VEN0002997 | E42: 925012043 | F42: H1D7ZT | G42: OSR9005DWESY2-2HB | H42: 925012043 | I42: -5 | J42: Минус | K42: Директни | L42: 46209 | M42: Ниво 3
A43: 27263 | B43: 14402 | C43: MOTO REMO BURZYŃSCY SP.J. | D43: VEN0001263 | E43: FAWZ0008732026 | F43: D92337 | G43: 709836-5005S | H43: FAWZ/000873/2026 | I43: 2 | J43: Плюс | K43: Директни | L43: 46206 | M43: Б. П.
A44: 27262 | B44: 14402 | C44: MOTO REMO BURZYŃSCY SP.J. | D44: VEN0001263 | E44: FAWZ0008732026 | F44: D9233F | G44: 765261-5008S | H44: FAWZ/000873/2026 | I44: -2 | J44: Минус | K44: Директни | L44: 46206 | M44: Б. П.
A45: 27402 | B45: 14270 | C45: NRF RO | D45: VEN0003798 | E45: SI-001121 | F45: G0K3N2 | G45: NRF 380057 | H45: DN000001213 | I45: 5 | J45: Плюс | K45: Директни | L45: 46204 | M45: Ниво 3
A46: 27399 | B46: 14270 | C46: NRF RO | D46: VEN0003798 | E46: SI-001121 | F46: G13XFN | G46: NRF 38620 | H46: DN000001213 | I46: 2 | J46: Плюс | K46: Директни | L46: 46204 | M46: Ниво 3
A47: 27397 | B47: 14270 | C47: NRF RO | D47: VEN0003798 | E47: SI-001121 | F47: G13WHT | G47: NRF 38738 | H47: DN000001213 | I47: -2 | J47: Минус | K47: Директни | L47: 46204 | M47: Ниво 3
A48: 27404 | B48: 14270 | C48: NRF RO | D48: VEN0003798 | E48: SI-001121 | F48: C3C9AA | G48: NRF 47387 | H48: DN000001213 | I48: 5 | J48: Плюс | K48: Директни | L48: 46204 | M48: Ниво 3
A49: 27405 | B49: 14270 | C49: NRF RO | D49: VEN0003798 | E49: SI-001121 | F49: G0V9FS | G49: NRF 48631 | H49: DN000001213 | I49: 1 | J49: Плюс | K49: Директни | L49: 46204 | M49: Ниво 3
A50: 27406 | B50: 14270 | C50: NRF RO | D50: VEN0003798 | E50: SI-001121 | F50: AE56E7 | G50: NRF 53267 | H50: DN000001213 | I50: 1 | J50: Плюс | K50: Директни | L50: 46204 | M50: Ниво 3
A51: 27407 | B51: 14270 | C51: NRF RO | D51: VEN0003798 | E51: SI-001121 | F51: AE578A | G51: NRF 53443 | H51: DN000001213 | I51: 2 | J51: Плюс | K51: Директни | L51: 46204 | M51: Ниво 3
A52: 27394 | B52: 14270 | C52: NRF RO | D52: VEN0003798 | E52: SI-001121 | F52: D8183F | G52: NRF 58472 | H52: DN000001213 | I52: -2 | J52: Минус | K52: Директни | L52: 46204 | M52: Ниво 3
A53: 27396 | B53: 14270 | C53: NRF RO | D53: VEN0003798 | E53: SI-001121 | F53: G0733V | G53: NRF 59282 | H53: DN000001213 | I53: -1 | J53: Минус | K53: Директни | L53: 46204 | M53: Ниво 3
A54: 27403 | B54: 14270 | C54: NRF RO | D54: VEN0003798 | E54: SI-001121 | F54: G0WMUC | G54: NRF 725236 | H54: DN000001213 | I54: 4 | J54: Плюс | K54: Директни | L54: 46204 | M54: Ниво 3
... A64: 27471 | B64: 14431 | C64: EXIDE TECH . -АКУМУЛАТОРИ | D64: VEN0001245 | E64: VVQ923795 | F64: BBDCB3 | G64: EA530 | H64: VVQ 923795 | I64: 30 | J64: Плюс | K64: Директни | L64: 46209 | M64: Палетна зона
A65: 27335 | B65: 14128 | C65: HIGHWAY AUTOMOTIVE SP. Z O.O. | D65: VEN0003634 | E65: WDT/2026/00687 | F65: H0HWRH | G65: 11033052HW | H65: 0 | I65: -1 | J65: Минус | K65: Директни | L65: 46199 | M65: Палетна зона
A66: 27458 | B66: 14403 | C66: LINEX SP. Z O.O. | D66: VEN0001286 | E66: WDT6072026 | F66: D2097D | G66: LIN47.44.04 | H66: WDT/607/2026 | I66: 1 | J66: Плюс | K66: Директни | L66: 46206 | M66: Ниво 3

Sheet работно поле
A1: 368512 | B1: | | D1: D06C2C | E1: | | F1: C 27 1250/1 | G1: -42 | I1: D06C2C | J1: 42 | K1: =G1+J1 -> 0
A2: C5D366 | B2: 52.39 | D2: H068NX | E2: | | F2: TB 1374/13 X | G2: -10 | I2: H068NX | J2: 10 | K2: =G2+J2 -> 0
A3: C00D83 | B3: 66.64 | D3: D06F44 | E3: | | F3: WP 12 300 | G3: -10 | I3: D06F44 | J3: 10 | K3: =G3+J3 -> 0
A4: G13XFN | B4: 30.8 | D4: G0QNP7 | E4: | | F4: VAL200284 | G4: -1 | I4: G0QNP7 | J4: 1 | K4: =G4+J4 -> 0
A5: AE56E7 | B5: 37.17 | D5: G0UYL7 | E5: | | F5: VAL440999 | G5: -1 | I5: G0UYL7 | J5: 1 | K5: =G5+J5 -> 0
A6: AE578A | B6: 43.65 | D6: F8E7A5 | E6: | | F6: VAL837437 | G6: -1 | I6: F8E7A5 | J6: 1 | K6: =G6+J6 -> 0
A7: G0K3M2 | B7: 147.97 | D7: AE9AAE | E7: | | F7: 20190390600 | G7: -1 | I7: AE9AAE | J7: 1 | K7: =G7+J7 -> 0
A8: G0YHEW | B8: 17.89 | D8: DE38D3 | E8: | | F8: 7.07381.00.0 | G8: -1 | I8: DE38D3 | J8: 1 | K8: =G8+J8 -> 0
A9: G0WNJF | B9: 18.28 | D9: G0KLIH | E9: | | F9: HP117 457 | G9: -12 | I9: G0KLIH | J9: 12 | K9: =G9+J9 -> 0
D10: D67AA0 | E10: | | F10: 5 PK 1150 K1 | G10: -6 | I10: D67AA0 | J10: 6 | K10: =G10+J10 -> 0
D11: B417A9 | E11: | | F11: 6 PK 1670 | G11: -5 | I11: B417A9 | J11: 5 | K11: =G11+J11 -> 0
D12: G1159K | E12: | | F12: CT 1162 WP5 | G12: -1 | I12: G1159K | J12: 1 | K12: =G12+J12 -> 0
D13: G0OC6W | E13: | | F13: BCV29264TK | G13: -5 | I13: G0OC6W | J13: 5 | K13: =G13+J13 -> 0
D14: 223620 | E14: | | F14: 08-245200-00 | G14: -10 | I14: 223620 | J14: 10 | K14: =G14+J14 -> 0
D15: D4876E | E15: | | F15: BCR214A | G15: -4 | I15: D4876E | J15: 4 | K15: =G15+J15 -> 0
D16: DC26DF | E16: | | F16: CH-LS-10133 | G16: -8 | I16: DC26DF | J16: 8 | K16: =G16+J16 -> 0
D17: 315186 | E17: | | F17: FVR1102 | G17: -9 | I17: 315186 | J17: 9 | K17: =G17+J17 -> 0
D18: G08FBW | E18: | | F18: CFF 471 000P | G18: -2 | I18: G08FBW | J18: 2 | K18: =G18+J18 -> 0
D19: F8248C | E19: | | F19: 544 0088 20 | G19: -5 | I19: F8248C | J19: 5 | K19: =G19+J19 -> 0
D20: D0B031 | E20: | | F20: 712 0580 10 | G20: -18 | I20: D0B031 | J20: 18 | K20: =G20+J20 -> 0
D21: G0X14X | E21: | | F21: FRG77409460 | G21: -2 | I21: G0X14X | J21: 2 | K21: =G21+J21 -> 0
D22: D75935 | E22: | | F22: MMT A040 00992W2 | G22: -2 | I22: D75935 | J22: 2 | K22: =G22+J22 -> 0
D23: D701DB | E23: | | F23: LMI36532 | G23: -2 | I23: D701DB | J23: 2 | K23: =G23+J23 -> 0
D24: B38D11 | E24: | | F24: GDB1736 | G24: -3 | I24: B38D11 | J24: 3 | K24: =G24+J24 -> 0
D25: BB905C | E25: | | F25: PHB562 | G25: -8 | I25: BB905C | J25: 8 | K25: =G25+J25 -> 0
D26: H07R6N | E26: | | F26: GATK04T360HOB | G26: -1 | I26: H07R6N | J26: 1 | K26: =G26+J26 -> 0
D27: E4D086 | E27: | | F27: GATK015537XS | G27: -5 | I27: E4D086 | J27: 5 | K27: =G27+J27 -> 0
D28: E65886 | E28: | | F28: NLX233 K10SZT | G28: -495 | I28: E65886 | J28: 495 | K28: =G28+J28 -> 0
D29: H0KLJA | E29: | | F29: OSR7506DWP-2BL | G29: -20 | I29: H0KLJA | J29: 20 | K29: =G29+J29 -> 0
... D39: 9F824A | E39: | | F39: AHP029MT | G39: -4 | I39: 9F824A | J39: 4 | K39: =G39+J39 -> 0
D40: H0HWRH | F40: 11033052HW | G40: -1 | I40: H0HWRH | J40: 1 | K40: =G40+J40 -> 0
